{
  "t": "2026-07-05T01:15:12.697Z",
  "r": 0,
  "lb": 30,
  "in": {
    "raw-materials": {
      "cv": 7234.5038,
      "pv": 7234.5038,
      "ch": 0
    },
    "industrial-goods": {
      "cv": 426.5873,
      "pv": 426.5873,
      "ch": 0
    },
    "consumer-goods": {
      "cv": 605.1998,
      "pv": 605.1998,
      "ch": 0
    },
    "energy-fuel": {
      "cv": 24.4624,
      "pv": 24.4624,
      "ch": 0
    },
    "electronics": {
      "cv": 1189.3054,
      "pv": 1189.3054,
      "ch": 0
    },
    "construction": {
      "cv": 1704.0389,
      "pv": 1704.0389,
      "ch": 0
    },
    "aerospace": {
      "cv": 4206.2582,
      "pv": 4206.2582,
      "ch": 0
    },
    "cpi": {
      "cv": 2198.6223,
      "pv": 2198.6223,
      "ch": 0
    },
    "core-cpi": {
      "cv": 2509.2165,
      "pv": 2509.2165,
      "ch": 0
    },
    "gdp": {
      "cv": 2053088559028,
      "pv": 2053088559028,
      "ch": 0
    }
  }
}
