{"t":"2026-05-27T00:20:09.362Z","r":0,"momentum":{"raw-materials":{"st":-51.26,"mt":-51.26,"ac":0,"s5":5328.9873,"m5":5328.9873,"ts":0},"industrial-goods":{"st":0.07,"mt":0.07,"ac":0,"s5":417.9215,"m5":417.9215,"ts":1},"consumer-goods":{"st":0.19,"mt":0.19,"ac":0,"s5":553.616,"m5":553.616,"ts":1},"energy-fuel":{"st":-2.37,"mt":-2.37,"ac":0,"s5":23.614,"m5":23.614,"ts":0},"electronics":{"st":-0.26,"mt":-0.26,"ac":0,"s5":1075.803,"m5":1075.803,"ts":0},"construction":{"st":0.26,"mt":0.26,"ac":0,"s5":1512.5417,"m5":1512.5417,"ts":1},"aerospace":{"st":-1.38,"mt":-1.38,"ac":0,"s5":3928.6858,"m5":3928.6858,"ts":0}},"stp":5,"mtp":20,"ok":true}

