{
  "pipelines": [
    {
      "avgDurationMs": 2,
      "failedRuns": 0,
      "lastOk": true,
      "lastRun": "2026-05-27T14:00:15.636Z",
      "name": "dashboard",
      "totalRuns": 8
    },
    {
      "avgDurationMs": 175686,
      "failedRuns": 4,
      "lastOk": false,
      "lastRun": "2026-05-27T14:00:15.635Z",
      "name": "macro",
      "totalRuns": 4
    },
    {
      "avgDurationMs": 6,
      "failedRuns": 3,
      "lastOk": true,
      "lastRun": "2026-05-27T14:00:15.635Z",
      "name": "intelligence",
      "totalRuns": 4
    },
    {
      "avgDurationMs": 8,
      "failedRuns": 0,
      "lastOk": true,
      "lastRun": "2026-05-27T14:00:15.635Z",
      "name": "relational",
      "totalRuns": 4
    }
  ]
}
