{
  "pipelines": [
    {
      "avgDurationMs": 2,
      "failedRuns": 0,
      "lastOk": true,
      "lastRun": "2026-06-09T04:25:08.533Z",
      "name": "dashboard",
      "totalRuns": 4
    },
    {
      "avgDurationMs": 452954,
      "failedRuns": 2,
      "lastOk": false,
      "lastRun": "2026-06-09T04:25:08.532Z",
      "name": "macro",
      "totalRuns": 2
    },
    {
      "avgDurationMs": 7,
      "failedRuns": 2,
      "lastOk": false,
      "lastRun": "2026-06-09T04:25:08.533Z",
      "name": "intelligence",
      "totalRuns": 2
    },
    {
      "avgDurationMs": 9,
      "failedRuns": 0,
      "lastOk": true,
      "lastRun": "2026-06-09T04:25:08.533Z",
      "name": "relational",
      "totalRuns": 2
    }
  ]
}
