{"pipelines":[{"name":"dashboard","lastRun":"2026-06-18T13:45:17.608Z","lastOk":true,"totalRuns":2,"failedRuns":0,"avgDurationMs":2},{"name":"macro","lastRun":"2026-06-18T13:45:17.607Z","lastOk":false,"totalRuns":1,"failedRuns":1,"avgDurationMs":856881},{"name":"intelligence","lastRun":"2026-06-18T13:45:17.608Z","lastOk":false,"totalRuns":1,"failedRuns":1,"avgDurationMs":7},{"name":"relational","lastRun":"2026-06-18T13:45:17.608Z","lastOk":true,"totalRuns":1,"failedRuns":0,"avgDurationMs":13}]}

