{
  "pipelines": [
    {
      "avgDurationMs": 3,
      "failedRuns": 0,
      "lastOk": true,
      "lastRun": "2026-06-26T18:55:13.475Z",
      "name": "dashboard",
      "totalRuns": 4
    },
    {
      "avgDurationMs": 304913,
      "failedRuns": 2,
      "lastOk": false,
      "lastRun": "2026-06-26T18:55:13.472Z",
      "name": "macro",
      "totalRuns": 2
    },
    {
      "avgDurationMs": 4,
      "failedRuns": 2,
      "lastOk": false,
      "lastRun": "2026-06-26T18:55:13.472Z",
      "name": "intelligence",
      "totalRuns": 2
    },
    {
      "avgDurationMs": 9,
      "failedRuns": 0,
      "lastOk": true,
      "lastRun": "2026-06-26T18:55:13.475Z",
      "name": "relational",
      "totalRuns": 2
    }
  ]
}
