{
  "both": {
    "100_0": {
      "nm": "Aerospace research",
      "vw": 129.9593
    },
    "101_0": {
      "nm": "Reinforced concrete",
      "vw": 217.1474
    },
    "102_0": {
      "nm": "Bricks",
      "vw": 2.8687
    },
    "104_0": {
      "nm": "Clay",
      "vw": 0.9982
    },
    "106_0": {
      "nm": "Wood",
      "vw": 4.444
    },
    "109_3": {
      "nm": "Windows",
      "vw": 119.8888
    },
    "111_0": {
      "nm": "Construction units",
      "vw": 2884.8677
    },
    "113_0": {
      "nm": "Materials research",
      "vw": 178.1946
    },
    "114_0": {
      "nm": "Robots",
      "vw": 905.9562
    },
    "115_0": {
      "nm": "Cows",
      "vw": 144.3406
    },
    "118_0": {
      "nm": "Coffee beans",
      "vw": 0.867
    },
    "119_9": {
      "nm": "Coffee powder",
      "vw": 63
    },
    "11_0": {
      "nm": "Petrol",
      "vw": 42.4453
    },
    "120_0": {
      "nm": "Vegetables",
      "vw": 2.9625
    },
    "121_0": {
      "nm": "Bread",
      "vw": 167.5225
    },
    "122_0": {
      "nm": "Cheese",
      "vw": 129.9311
    },
    "124_0": {
      "nm": "Orange juice",
      "vw": 39.4696
    },
    "125_0": {
      "nm": "Apple cider",
      "vw": 28.5954
    },
    "125_4": {
      "nm": "Apple cider",
      "vw": 39.8309
    },
    "126_0": {
      "nm": "Ginger beer",
      "vw": 58.5221
    },
    "127_0": {
      "nm": "Frozen pizza",
      "vw": 458.4013
    },
    "128_0": {
      "nm": "Pasta",
      "vw": 57.8247
    },
    "130_0": {
      "nm": "Lasagna",
      "vw": 2345.4546
    },
    "131_0": {
      "nm": "Meat balls",
      "vw": 2695.5618
    },
    "136_0": {
      "nm": "Cocoa",
      "vw": 1.9342
    },
    "137_0": {
      "nm": "Dough",
      "vw": 135.3677
    },
    "138_0": {
      "nm": "Sauce",
      "vw": 1540
    },
    "139_0": {
      "nm": "Fodder",
      "vw": 11.1251
    },
    "13_0": {
      "nm": "Transport",
      "vw": 0.4017
    },
    "142_0": {
      "nm": "Salad",
      "vw": 912.9927
    },
    "143_0": {
      "nm": "Samosa",
      "vw": 751.9652
    },
    "145_0": {
      "nm": "Recipes",
      "vw": 171.6711
    },
    "146_0": {
      "nm": "Pumpkin",
      "vw": 12.1128
    },
    "148_0": {
      "nm": "Witch costume",
      "vw": 33
    },
    "149_0": {
      "nm": "Pumpkin soup",
      "vw": 906.0455
    },
    "14_0": {
      "nm": "Minerals",
      "vw": 12.3878
    },
    "150_0": {
      "nm": "Tree",
      "vw": 447.2968
    },
    "153_0": {
      "nm": "Chocolate icecream",
      "vw": 75
    },
    "15_4": {
      "nm": "Bauxite",
      "vw": 13.046
    },
    "17_0": {
      "nm": "Chemicals",
      "vw": 16.0715
    },
    "18_0": {
      "nm": "Aluminium",
      "vw": 23.3015
    },
    "18_1": {
      "nm": "Aluminium",
      "vw": 23.4916
    },
    "18_2": {
      "nm": "Aluminium",
      "vw": 24.2392
    },
    "18_3": {
      "nm": "Aluminium",
      "vw": 24.743
    },
    "18_4": {
      "nm": "Aluminium",
      "vw": 25.2092
    },
    "18_5": {
      "nm": "Aluminium",
      "vw": 25.5644
    },
    "18_6": {
      "nm": "Aluminium",
      "vw": 25.6051
    },
    "18_7": {
      "nm": "Aluminium",
      "vw": 26.0924
    },
    "18_8": {
      "nm": "Aluminium",
      "vw": 26.25
    },
    "19_0": {
      "nm": "Plastic",
      "vw": 13.7306
    },
    "1_0": {
      "nm": "Power",
      "vw": 0.2805
    },
    "21_0": {
      "nm": "Electronic components",
      "vw": 62.8272
    },
    "22_0": {
      "nm": "Batteries",
      "vw": 93.6033
    },
    "23_0": {
      "nm": "Displays",
      "vw": 132.5212
    },
    "24_0": {
      "nm": "Smart phones",
      "vw": 691.0264
    },
    "25_0": {
      "nm": "Tablets",
      "vw": 835.0925
    },
    "27_4": {
      "nm": "Monitors",
      "vw": 666.4609
    },
    "29_0": {
      "nm": "Plant research",
      "vw": 124.9675
    },
    "2_0": {
      "nm": "Water",
      "vw": 0.3856
    },
    "31_0": {
      "nm": "Mining research",
      "vw": 249.4149
    },
    "32_0": {
      "nm": "Electronics research",
      "vw": 293.1587
    },
    "33_0": {
      "nm": "Breeding research",
      "vw": 141.2867
    },
    "35_0": {
      "nm": "Software",
      "vw": 110.5728
    },
    "3_0": {
      "nm": "Apples",
      "vw": 2.5888
    },
    "40_0": {
      "nm": "Cotton",
      "vw": 1.7361
    },
    "41_0": {
      "nm": "Fabric",
      "vw": 5.8138
    },
    "43_0": {
      "nm": "Steel",
      "vw": 13.2122
    },
    "45_4": {
      "nm": "Glass",
      "vw": 15.3067
    },
    "46_0": {
      "nm": "Leather",
      "vw": 30.2149
    },
    "47_0": {
      "nm": "On-board computer",
      "vw": 511.6881
    },
    "49_0": {
      "nm": "Luxury car interior",
      "vw": 1071.8916
    },
    "4_4": {
      "nm": "Oranges",
      "vw": 3.3697
    },
    "50_0": {
      "nm": "Basic interior",
      "vw": 365.2396
    },
    "51_0": {
      "nm": "Car body",
      "vw": 869.0349
    },
    "53_0": {
      "nm": "Economy e-car",
      "vw": 3662.6667
    },
    "54_0": {
      "nm": "Luxury e-car",
      "vw": 7012.909
    },
    "55_0": {
      "nm": "Economy car",
      "vw": 2466.8994
    },
    "57_0": {
      "nm": "Truck",
      "vw": 6095.122
    },
    "59_0": {
      "nm": "Fashion research",
      "vw": 80.8363
    },
    "62_4": {
      "nm": "Dress",
      "vw": 27.5
    },
    "63_0": {
      "nm": "Stiletto Heel",
      "vw": 37.8719
    },
    "64_0": {
      "nm": "Handbags",
      "vw": 51.5176
    },
    "65_0": {
      "nm": "Sneakers",
      "vw": 17.3184
    },
    "66_0": {
      "nm": "Seeds",
      "vw": 0.2981
    },
    "69_0": {
      "nm": "Golden bars",
      "vw": 6556.2393
    },
    "6_0": {
      "nm": "Grain",
      "vw": 0.7434
    },
    "72_0": {
      "nm": "Sugarcane",
      "vw": 1.7355
    },
    "75_9": {
      "nm": "Carbon fibers",
      "vw": 7.8
    },
    "76_0": {
      "nm": "Carbon composite",
      "vw": 66.2771
    },
    "77_0": {
      "nm": "Fuselage",
      "vw": 2929.2957
    },
    "79_0": {
      "nm": "High grade e-comps",
      "vw": 1006.0771
    },
    "82_0": {
      "nm": "Attitude control",
      "vw": 1703.2117
    },
    "83_0": {
      "nm": "Rocket fuel",
      "vw": 32.3718
    },
    "87_0": {
      "nm": "Heat shield",
      "vw": 558.4167
    },
    "88_4": {
      "nm": "Ion drive",
      "vw": 15120.085
    },
    "89_0": {
      "nm": "Jet engine",
      "vw": 5412.1494
    },
    "8_0": {
      "nm": "Sausages",
      "vw": 13.3372
    },
    "9_4": {
      "nm": "Eggs",
      "vw": 1.4961
    }
  },
  "overall": {
    "n": 79,
    "vw": 745.2227
  },
  "product": {
    "1": {
      "nm": "Power",
      "vw": 0.2805
    },
    "100": {
      "nm": "Aerospace research",
      "vw": 129.9593
    },
    "101": {
      "nm": "Reinforced concrete",
      "vw": 217.1474
    },
    "102": {
      "nm": "Bricks",
      "vw": 2.8687
    },
    "104": {
      "nm": "Clay",
      "vw": 0.9982
    },
    "106": {
      "nm": "Wood",
      "vw": 4.444
    },
    "11": {
      "nm": "Petrol",
      "vw": 42.4453
    },
    "111": {
      "nm": "Construction units",
      "vw": 2884.8677
    },
    "113": {
      "nm": "Materials research",
      "vw": 178.1946
    },
    "114": {
      "nm": "Robots",
      "vw": 905.9562
    },
    "115": {
      "nm": "Cows",
      "vw": 144.3406
    },
    "118": {
      "nm": "Coffee beans",
      "vw": 0.867
    },
    "120": {
      "nm": "Vegetables",
      "vw": 2.9625
    },
    "121": {
      "nm": "Bread",
      "vw": 167.5225
    },
    "122": {
      "nm": "Cheese",
      "vw": 129.9311
    },
    "124": {
      "nm": "Orange juice",
      "vw": 39.4696
    },
    "125": {
      "nm": "Apple cider",
      "vw": 28.5954
    },
    "126": {
      "nm": "Ginger beer",
      "vw": 58.5221
    },
    "127": {
      "nm": "Frozen pizza",
      "vw": 458.4013
    },
    "128": {
      "nm": "Pasta",
      "vw": 57.8247
    },
    "13": {
      "nm": "Transport",
      "vw": 0.4017
    },
    "130": {
      "nm": "Lasagna",
      "vw": 2345.4546
    },
    "131": {
      "nm": "Meat balls",
      "vw": 2695.5618
    },
    "136": {
      "nm": "Cocoa",
      "vw": 1.9342
    },
    "137": {
      "nm": "Dough",
      "vw": 135.3677
    },
    "138": {
      "nm": "Sauce",
      "vw": 1540
    },
    "139": {
      "nm": "Fodder",
      "vw": 11.1251
    },
    "14": {
      "nm": "Minerals",
      "vw": 12.3878
    },
    "142": {
      "nm": "Salad",
      "vw": 912.9927
    },
    "143": {
      "nm": "Samosa",
      "vw": 751.9652
    },
    "145": {
      "nm": "Recipes",
      "vw": 171.6711
    },
    "146": {
      "nm": "Pumpkin",
      "vw": 12.1128
    },
    "148": {
      "nm": "Witch costume",
      "vw": 33
    },
    "149": {
      "nm": "Pumpkin soup",
      "vw": 906.0455
    },
    "150": {
      "nm": "Tree",
      "vw": 447.2968
    },
    "153": {
      "nm": "Chocolate icecream",
      "vw": 75
    },
    "17": {
      "nm": "Chemicals",
      "vw": 16.0715
    },
    "18": {
      "nm": "Aluminium",
      "vw": 23.3015
    },
    "19": {
      "nm": "Plastic",
      "vw": 13.7306
    },
    "2": {
      "nm": "Water",
      "vw": 0.3856
    },
    "21": {
      "nm": "Electronic components",
      "vw": 62.8272
    },
    "22": {
      "nm": "Batteries",
      "vw": 93.6033
    },
    "23": {
      "nm": "Displays",
      "vw": 132.5212
    },
    "24": {
      "nm": "Smart phones",
      "vw": 691.0264
    },
    "25": {
      "nm": "Tablets",
      "vw": 835.0925
    },
    "29": {
      "nm": "Plant research",
      "vw": 124.9675
    },
    "3": {
      "nm": "Apples",
      "vw": 2.5888
    },
    "31": {
      "nm": "Mining research",
      "vw": 249.4149
    },
    "32": {
      "nm": "Electronics research",
      "vw": 293.1587
    },
    "33": {
      "nm": "Breeding research",
      "vw": 141.2867
    },
    "35": {
      "nm": "Software",
      "vw": 110.5728
    },
    "40": {
      "nm": "Cotton",
      "vw": 1.7361
    },
    "41": {
      "nm": "Fabric",
      "vw": 5.8138
    },
    "43": {
      "nm": "Steel",
      "vw": 13.2122
    },
    "46": {
      "nm": "Leather",
      "vw": 30.2149
    },
    "47": {
      "nm": "On-board computer",
      "vw": 511.6881
    },
    "49": {
      "nm": "Luxury car interior",
      "vw": 1071.8916
    },
    "50": {
      "nm": "Basic interior",
      "vw": 365.2396
    },
    "51": {
      "nm": "Car body",
      "vw": 869.0349
    },
    "53": {
      "nm": "Economy e-car",
      "vw": 3662.6667
    },
    "54": {
      "nm": "Luxury e-car",
      "vw": 7012.909
    },
    "55": {
      "nm": "Economy car",
      "vw": 2466.8994
    },
    "57": {
      "nm": "Truck",
      "vw": 6095.122
    },
    "59": {
      "nm": "Fashion research",
      "vw": 80.8363
    },
    "6": {
      "nm": "Grain",
      "vw": 0.7434
    },
    "63": {
      "nm": "Stiletto Heel",
      "vw": 37.8719
    },
    "64": {
      "nm": "Handbags",
      "vw": 51.5176
    },
    "65": {
      "nm": "Sneakers",
      "vw": 17.3184
    },
    "66": {
      "nm": "Seeds",
      "vw": 0.2981
    },
    "69": {
      "nm": "Golden bars",
      "vw": 6556.2393
    },
    "72": {
      "nm": "Sugarcane",
      "vw": 1.7355
    },
    "76": {
      "nm": "Carbon composite",
      "vw": 66.2771
    },
    "77": {
      "nm": "Fuselage",
      "vw": 2929.2957
    },
    "79": {
      "nm": "High grade e-comps",
      "vw": 1006.0771
    },
    "8": {
      "nm": "Sausages",
      "vw": 13.3372
    },
    "82": {
      "nm": "Attitude control",
      "vw": 1703.2117
    },
    "83": {
      "nm": "Rocket fuel",
      "vw": 32.3718
    },
    "87": {
      "nm": "Heat shield",
      "vw": 558.4167
    },
    "89": {
      "nm": "Jet engine",
      "vw": 5412.1494
    }
  },
  "quality": {
    "0": {
      "n": 79,
      "vw": 745.2227
    },
    "1": {
      "n": 1,
      "vw": 23.4916
    },
    "2": {
      "n": 1,
      "vw": 24.2392
    },
    "3": {
      "n": 2,
      "vw": 72.3159
    },
    "4": {
      "n": 9,
      "vw": 1768.0338
    },
    "5": {
      "n": 1,
      "vw": 25.5644
    },
    "6": {
      "n": 1,
      "vw": 25.6051
    },
    "7": {
      "n": 1,
      "vw": 26.0924
    },
    "8": {
      "n": 1,
      "vw": 26.25
    },
    "9": {
      "n": 2,
      "vw": 35.4
    }
  },
  "r": 0,
  "t": "2026-03-07"
}
