{
  "both": {
    "100_0": {
      "nm": "Aerospace research",
      "vw": 126.8875
    },
    "101_0": {
      "nm": "Reinforced concrete",
      "vw": 198.1025
    },
    "101_1": {
      "nm": "Reinforced concrete",
      "vw": 198.7315
    },
    "101_2": {
      "nm": "Reinforced concrete",
      "vw": 199.2575
    },
    "101_3": {
      "nm": "Reinforced concrete",
      "vw": 199.7264
    },
    "101_4": {
      "nm": "Reinforced concrete",
      "vw": 200.1822
    },
    "101_5": {
      "nm": "Reinforced concrete",
      "vw": 198.7914
    },
    "102_0": {
      "nm": "Bricks",
      "vw": 2.751
    },
    "102_1": {
      "nm": "Bricks",
      "vw": 2.7808
    },
    "102_10": {
      "nm": "Bricks",
      "vw": 3.45
    },
    "102_12": {
      "nm": "Bricks",
      "vw": 3.5
    },
    "102_2": {
      "nm": "Bricks",
      "vw": 2.7778
    },
    "102_3": {
      "nm": "Bricks",
      "vw": 2.799
    },
    "102_4": {
      "nm": "Bricks",
      "vw": 2.905
    },
    "102_5": {
      "nm": "Bricks",
      "vw": 2.9786
    },
    "102_6": {
      "nm": "Bricks",
      "vw": 2.8427
    },
    "102_7": {
      "nm": "Bricks",
      "vw": 3.2
    },
    "102_8": {
      "nm": "Bricks",
      "vw": 3.15
    },
    "103_0": {
      "nm": "Cement",
      "vw": 6.8792
    },
    "103_1": {
      "nm": "Cement",
      "vw": 6.861
    },
    "103_10": {
      "nm": "Cement",
      "vw": 7.8
    },
    "103_11": {
      "nm": "Cement",
      "vw": 9.7
    },
    "103_2": {
      "nm": "Cement",
      "vw": 6.9751
    },
    "103_3": {
      "nm": "Cement",
      "vw": 6.9967
    },
    "103_4": {
      "nm": "Cement",
      "vw": 7.2499
    },
    "103_5": {
      "nm": "Cement",
      "vw": 7.4509
    },
    "103_6": {
      "nm": "Cement",
      "vw": 7.7
    },
    "103_7": {
      "nm": "Cement",
      "vw": 7.7175
    },
    "103_8": {
      "nm": "Cement",
      "vw": 7.5
    },
    "104_0": {
      "nm": "Clay",
      "vw": 1.0562
    },
    "104_1": {
      "nm": "Clay",
      "vw": 1.0479
    },
    "104_10": {
      "nm": "Clay",
      "vw": 2.45
    },
    "104_11": {
      "nm": "Clay",
      "vw": 1.5
    },
    "104_2": {
      "nm": "Clay",
      "vw": 1.0761
    },
    "104_3": {
      "nm": "Clay",
      "vw": 1.7261
    },
    "104_4": {
      "nm": "Clay",
      "vw": 1.1406
    },
    "104_5": {
      "nm": "Clay",
      "vw": 1.7
    },
    "104_7": {
      "nm": "Clay",
      "vw": 2.1613
    },
    "105_0": {
      "nm": "Limestone",
      "vw": 1.6392
    },
    "105_1": {
      "nm": "Limestone",
      "vw": 1.7013
    },
    "105_10": {
      "nm": "Limestone",
      "vw": 1.99
    },
    "105_2": {
      "nm": "Limestone",
      "vw": 1.7282
    },
    "105_3": {
      "nm": "Limestone",
      "vw": 1.7135
    },
    "105_4": {
      "nm": "Limestone",
      "vw": 1.73
    },
    "105_5": {
      "nm": "Limestone",
      "vw": 1.7417
    },
    "105_6": {
      "nm": "Limestone",
      "vw": 1.67
    },
    "105_7": {
      "nm": "Limestone",
      "vw": 1.68
    },
    "106_0": {
      "nm": "Wood",
      "vw": 3.8901
    },
    "106_1": {
      "nm": "Wood",
      "vw": 4.0231
    },
    "106_2": {
      "nm": "Wood",
      "vw": 4.4432
    },
    "106_3": {
      "nm": "Wood",
      "vw": 4.4489
    },
    "106_4": {
      "nm": "Wood",
      "vw": 4.515
    },
    "106_5": {
      "nm": "Wood",
      "vw": 4.65
    },
    "107_0": {
      "nm": "Beams",
      "vw": 21.406
    },
    "107_1": {
      "nm": "Beams",
      "vw": 21.7678
    },
    "107_2": {
      "nm": "Beams",
      "vw": 21.7349
    },
    "107_3": {
      "nm": "Beams",
      "vw": 22.1688
    },
    "107_4": {
      "nm": "Beams",
      "vw": 22.8835
    },
    "107_6": {
      "nm": "Beams",
      "vw": 22.1282
    },
    "108_0": {
      "nm": "Planks",
      "vw": 9.9666
    },
    "108_1": {
      "nm": "Planks",
      "vw": 9.9812
    },
    "108_2": {
      "nm": "Planks",
      "vw": 9.9989
    },
    "108_3": {
      "nm": "Planks",
      "vw": 10.0386
    },
    "108_4": {
      "nm": "Planks",
      "vw": 10.0689
    },
    "108_5": {
      "nm": "Planks",
      "vw": 10.4
    },
    "108_6": {
      "nm": "Planks",
      "vw": 10.8
    },
    "109_0": {
      "nm": "Windows",
      "vw": 113.4606
    },
    "109_1": {
      "nm": "Windows",
      "vw": 114.6331
    },
    "109_2": {
      "nm": "Windows",
      "vw": 114.0984
    },
    "109_3": {
      "nm": "Windows",
      "vw": 115.0213
    },
    "109_4": {
      "nm": "Windows",
      "vw": 113.6489
    },
    "109_5": {
      "nm": "Windows",
      "vw": 116.1707
    },
    "109_6": {
      "nm": "Windows",
      "vw": 142.5038
    },
    "109_7": {
      "nm": "Windows",
      "vw": 150
    },
    "109_8": {
      "nm": "Windows",
      "vw": 119
    },
    "10_0": {
      "nm": "Crude oil",
      "vw": 30.7267
    },
    "10_1": {
      "nm": "Crude oil",
      "vw": 31.1384
    },
    "10_10": {
      "nm": "Crude oil",
      "vw": 32.2767
    },
    "10_11": {
      "nm": "Crude oil",
      "vw": 32.3829
    },
    "10_12": {
      "nm": "Crude oil",
      "vw": 32
    },
    "10_2": {
      "nm": "Crude oil",
      "vw": 31.2559
    },
    "10_3": {
      "nm": "Crude oil",
      "vw": 31.5843
    },
    "10_4": {
      "nm": "Crude oil",
      "vw": 31.6825
    },
    "10_5": {
      "nm": "Crude oil",
      "vw": 31.864
    },
    "10_6": {
      "nm": "Crude oil",
      "vw": 32.0365
    },
    "10_7": {
      "nm": "Crude oil",
      "vw": 32.0949
    },
    "10_8": {
      "nm": "Crude oil",
      "vw": 33.5
    },
    "10_9": {
      "nm": "Crude oil",
      "vw": 33.0319
    },
    "110_0": {
      "nm": "Tools",
      "vw": 205.5737
    },
    "110_1": {
      "nm": "Tools",
      "vw": 209.3108
    },
    "110_2": {
      "nm": "Tools",
      "vw": 208.5009
    },
    "110_3": {
      "nm": "Tools",
      "vw": 207.3646
    },
    "110_4": {
      "nm": "Tools",
      "vw": 209.2058
    },
    "110_5": {
      "nm": "Tools",
      "vw": 208
    },
    "110_6": {
      "nm": "Tools",
      "vw": 280
    },
    "111_0": {
      "nm": "Construction units",
      "vw": 2674.2778
    },
    "112_0": {
      "nm": "Bulldozer",
      "vw": 2354.9133
    },
    "112_1": {
      "nm": "Bulldozer",
      "vw": 2354.713
    },
    "112_2": {
      "nm": "Bulldozer",
      "vw": 2356.5051
    },
    "112_3": {
      "nm": "Bulldozer",
      "vw": 2361.251
    },
    "112_4": {
      "nm": "Bulldozer",
      "vw": 2150
    },
    "113_0": {
      "nm": "Materials research",
      "vw": 148.801
    },
    "114_0": {
      "nm": "Robots",
      "vw": 647.0446
    },
    "114_1": {
      "nm": "Robots",
      "vw": 898.7947
    },
    "114_10": {
      "nm": "Robots",
      "vw": 2980
    },
    "114_12": {
      "nm": "Robots",
      "vw": 2991.6667
    },
    "114_2": {
      "nm": "Robots",
      "vw": 906.2268
    },
    "114_3": {
      "nm": "Robots",
      "vw": 911.4157
    },
    "114_4": {
      "nm": "Robots",
      "vw": 911.871
    },
    "114_5": {
      "nm": "Robots",
      "vw": 954.7372
    },
    "114_6": {
      "nm": "Robots",
      "vw": 990
    },
    "114_7": {
      "nm": "Robots",
      "vw": 1290
    },
    "114_8": {
      "nm": "Robots",
      "vw": 2081.0227
    },
    "114_9": {
      "nm": "Robots",
      "vw": 2670
    },
    "115_0": {
      "nm": "Cows",
      "vw": 129.8444
    },
    "115_1": {
      "nm": "Cows",
      "vw": 136.9474
    },
    "115_10": {
      "nm": "Cows",
      "vw": 268
    },
    "115_2": {
      "nm": "Cows",
      "vw": 143.0822
    },
    "115_3": {
      "nm": "Cows",
      "vw": 145.1726
    },
    "115_4": {
      "nm": "Cows",
      "vw": 148.0704
    },
    "115_5": {
      "nm": "Cows",
      "vw": 155.5977
    },
    "115_6": {
      "nm": "Cows",
      "vw": 162.6866
    },
    "115_7": {
      "nm": "Cows",
      "vw": 169
    },
    "116_0": {
      "nm": "Pigs",
      "vw": 41.9601
    },
    "116_1": {
      "nm": "Pigs",
      "vw": 42.0913
    },
    "116_2": {
      "nm": "Pigs",
      "vw": 44.9835
    },
    "116_3": {
      "nm": "Pigs",
      "vw": 47.9236
    },
    "116_4": {
      "nm": "Pigs",
      "vw": 50.999
    },
    "116_5": {
      "nm": "Pigs",
      "vw": 51.5
    },
    "116_6": {
      "nm": "Pigs",
      "vw": 70
    },
    "117_0": {
      "nm": "Milk",
      "vw": 8.0181
    },
    "117_1": {
      "nm": "Milk",
      "vw": 8.4898
    },
    "117_10": {
      "nm": "Milk",
      "vw": 16.1828
    },
    "117_11": {
      "nm": "Milk",
      "vw": 15.8
    },
    "117_12": {
      "nm": "Milk",
      "vw": 20
    },
    "117_2": {
      "nm": "Milk",
      "vw": 8.564
    },
    "117_3": {
      "nm": "Milk",
      "vw": 9.1758
    },
    "117_4": {
      "nm": "Milk",
      "vw": 9.5579
    },
    "117_5": {
      "nm": "Milk",
      "vw": 10.3937
    },
    "117_6": {
      "nm": "Milk",
      "vw": 11.5648
    },
    "117_7": {
      "nm": "Milk",
      "vw": 12.7
    },
    "117_8": {
      "nm": "Milk",
      "vw": 12.4362
    },
    "117_9": {
      "nm": "Milk",
      "vw": 15.5
    },
    "118_0": {
      "nm": "Coffee beans",
      "vw": 0.8378
    },
    "118_1": {
      "nm": "Coffee beans",
      "vw": 0.9073
    },
    "118_10": {
      "nm": "Coffee beans",
      "vw": 2
    },
    "118_2": {
      "nm": "Coffee beans",
      "vw": 0.9442
    },
    "118_3": {
      "nm": "Coffee beans",
      "vw": 0.9816
    },
    "118_4": {
      "nm": "Coffee beans",
      "vw": 1.0236
    },
    "118_5": {
      "nm": "Coffee beans",
      "vw": 1.2
    },
    "118_6": {
      "nm": "Coffee beans",
      "vw": 1.4233
    },
    "118_8": {
      "nm": "Coffee beans",
      "vw": 1.5
    },
    "119_0": {
      "nm": "Coffee powder",
      "vw": 34.5965
    },
    "119_1": {
      "nm": "Coffee powder",
      "vw": 35.9028
    },
    "119_10": {
      "nm": "Coffee powder",
      "vw": 59.7729
    },
    "119_11": {
      "nm": "Coffee powder",
      "vw": 73
    },
    "119_12": {
      "nm": "Coffee powder",
      "vw": 72.7936
    },
    "119_2": {
      "nm": "Coffee powder",
      "vw": 39.7838
    },
    "119_3": {
      "nm": "Coffee powder",
      "vw": 40.2698
    },
    "119_4": {
      "nm": "Coffee powder",
      "vw": 43.2542
    },
    "119_5": {
      "nm": "Coffee powder",
      "vw": 46.5227
    },
    "119_6": {
      "nm": "Coffee powder",
      "vw": 55.3574
    },
    "119_7": {
      "nm": "Coffee powder",
      "vw": 59.2686
    },
    "119_8": {
      "nm": "Coffee powder",
      "vw": 64.5
    },
    "119_9": {
      "nm": "Coffee powder",
      "vw": 65
    },
    "11_0": {
      "nm": "Petrol",
      "vw": 42.7692
    },
    "11_1": {
      "nm": "Petrol",
      "vw": 43.6926
    },
    "11_10": {
      "nm": "Petrol",
      "vw": 46.75
    },
    "11_11": {
      "nm": "Petrol",
      "vw": 48.7351
    },
    "11_2": {
      "nm": "Petrol",
      "vw": 43.8405
    },
    "11_3": {
      "nm": "Petrol",
      "vw": 44.4967
    },
    "11_4": {
      "nm": "Petrol",
      "vw": 45.2504
    },
    "11_5": {
      "nm": "Petrol",
      "vw": 46
    },
    "11_6": {
      "nm": "Petrol",
      "vw": 45
    },
    "11_7": {
      "nm": "Petrol",
      "vw": 46.5
    },
    "120_0": {
      "nm": "Vegetables",
      "vw": 2.7038
    },
    "120_1": {
      "nm": "Vegetables",
      "vw": 3.1653
    },
    "120_10": {
      "nm": "Vegetables",
      "vw": 6
    },
    "120_11": {
      "nm": "Vegetables",
      "vw": 7.5
    },
    "120_2": {
      "nm": "Vegetables",
      "vw": 3.2133
    },
    "120_3": {
      "nm": "Vegetables",
      "vw": 3.3316
    },
    "120_4": {
      "nm": "Vegetables",
      "vw": 3.2252
    },
    "120_5": {
      "nm": "Vegetables",
      "vw": 3.3888
    },
    "120_6": {
      "nm": "Vegetables",
      "vw": 3.4645
    },
    "120_7": {
      "nm": "Vegetables",
      "vw": 4.831
    },
    "120_8": {
      "nm": "Vegetables",
      "vw": 6.2167
    },
    "120_9": {
      "nm": "Vegetables",
      "vw": 6.9
    },
    "121_0": {
      "nm": "Bread",
      "vw": 152.6942
    },
    "121_1": {
      "nm": "Bread",
      "vw": 168.8529
    },
    "121_10": {
      "nm": "Bread",
      "vw": 280
    },
    "121_11": {
      "nm": "Bread",
      "vw": 285.918
    },
    "121_12": {
      "nm": "Bread",
      "vw": 320
    },
    "121_2": {
      "nm": "Bread",
      "vw": 182.583
    },
    "121_3": {
      "nm": "Bread",
      "vw": 214.6897
    },
    "121_4": {
      "nm": "Bread",
      "vw": 222
    },
    "121_5": {
      "nm": "Bread",
      "vw": 219.4804
    },
    "121_6": {
      "nm": "Bread",
      "vw": 236.8265
    },
    "121_7": {
      "nm": "Bread",
      "vw": 240.4259
    },
    "121_8": {
      "nm": "Bread",
      "vw": 248
    },
    "121_9": {
      "nm": "Bread",
      "vw": 270
    },
    "122_0": {
      "nm": "Cheese",
      "vw": 132.956
    },
    "122_1": {
      "nm": "Cheese",
      "vw": 134.9277
    },
    "122_10": {
      "nm": "Cheese",
      "vw": 198
    },
    "122_11": {
      "nm": "Cheese",
      "vw": 216.4867
    },
    "122_12": {
      "nm": "Cheese",
      "vw": 210.3222
    },
    "122_2": {
      "nm": "Cheese",
      "vw": 137.0432
    },
    "122_3": {
      "nm": "Cheese",
      "vw": 141.3033
    },
    "122_4": {
      "nm": "Cheese",
      "vw": 142.5857
    },
    "122_5": {
      "nm": "Cheese",
      "vw": 148.7832
    },
    "122_6": {
      "nm": "Cheese",
      "vw": 154.287
    },
    "122_7": {
      "nm": "Cheese",
      "vw": 155.6659
    },
    "122_8": {
      "nm": "Cheese",
      "vw": 165.5458
    },
    "122_9": {
      "nm": "Cheese",
      "vw": 184.5532
    },
    "123_0": {
      "nm": "Apple pie",
      "vw": 319.874
    },
    "123_1": {
      "nm": "Apple pie",
      "vw": 321.7675
    },
    "123_12": {
      "nm": "Apple pie",
      "vw": 600
    },
    "123_2": {
      "nm": "Apple pie",
      "vw": 321.3466
    },
    "123_3": {
      "nm": "Apple pie",
      "vw": 325.9502
    },
    "123_4": {
      "nm": "Apple pie",
      "vw": 327.7782
    },
    "123_5": {
      "nm": "Apple pie",
      "vw": 331.7082
    },
    "123_6": {
      "nm": "Apple pie",
      "vw": 343.12
    },
    "123_7": {
      "nm": "Apple pie",
      "vw": 346
    },
    "123_8": {
      "nm": "Apple pie",
      "vw": 356
    },
    "123_9": {
      "nm": "Apple pie",
      "vw": 375.3402
    },
    "124_0": {
      "nm": "Orange juice",
      "vw": 38.066
    },
    "124_1": {
      "nm": "Orange juice",
      "vw": 38.0285
    },
    "124_10": {
      "nm": "Orange juice",
      "vw": 71.7832
    },
    "124_11": {
      "nm": "Orange juice",
      "vw": 78.4555
    },
    "124_12": {
      "nm": "Orange juice",
      "vw": 100
    },
    "124_2": {
      "nm": "Orange juice",
      "vw": 38.6049
    },
    "124_3": {
      "nm": "Orange juice",
      "vw": 39.7493
    },
    "124_4": {
      "nm": "Orange juice",
      "vw": 41.9333
    },
    "124_5": {
      "nm": "Orange juice",
      "vw": 45.095
    },
    "124_6": {
      "nm": "Orange juice",
      "vw": 49.3848
    },
    "124_7": {
      "nm": "Orange juice",
      "vw": 53.8946
    },
    "124_8": {
      "nm": "Orange juice",
      "vw": 57
    },
    "124_9": {
      "nm": "Orange juice",
      "vw": 72.5
    },
    "125_0": {
      "nm": "Apple cider",
      "vw": 26.9784
    },
    "125_1": {
      "nm": "Apple cider",
      "vw": 28.0381
    },
    "125_10": {
      "nm": "Apple cider",
      "vw": 59.9367
    },
    "125_11": {
      "nm": "Apple cider",
      "vw": 61.6667
    },
    "125_12": {
      "nm": "Apple cider",
      "vw": 70
    },
    "125_2": {
      "nm": "Apple cider",
      "vw": 27.9086
    },
    "125_3": {
      "nm": "Apple cider",
      "vw": 32.4838
    },
    "125_4": {
      "nm": "Apple cider",
      "vw": 40.3991
    },
    "125_5": {
      "nm": "Apple cider",
      "vw": 46.435
    },
    "125_6": {
      "nm": "Apple cider",
      "vw": 48.124
    },
    "125_7": {
      "nm": "Apple cider",
      "vw": 48.468
    },
    "125_8": {
      "nm": "Apple cider",
      "vw": 53
    },
    "125_9": {
      "nm": "Apple cider",
      "vw": 59.5
    },
    "126_0": {
      "nm": "Ginger beer",
      "vw": 53.9331
    },
    "126_1": {
      "nm": "Ginger beer",
      "vw": 54.8491
    },
    "126_10": {
      "nm": "Ginger beer",
      "vw": 86.5788
    },
    "126_11": {
      "nm": "Ginger beer",
      "vw": 93
    },
    "126_12": {
      "nm": "Ginger beer",
      "vw": 97.0631
    },
    "126_2": {
      "nm": "Ginger beer",
      "vw": 54.7636
    },
    "126_3": {
      "nm": "Ginger beer",
      "vw": 55.8819
    },
    "126_4": {
      "nm": "Ginger beer",
      "vw": 58.1941
    },
    "126_5": {
      "nm": "Ginger beer",
      "vw": 66.7858
    },
    "126_6": {
      "nm": "Ginger beer",
      "vw": 69.6711
    },
    "126_7": {
      "nm": "Ginger beer",
      "vw": 69.591
    },
    "126_8": {
      "nm": "Ginger beer",
      "vw": 79.9995
    },
    "126_9": {
      "nm": "Ginger beer",
      "vw": 89.5
    },
    "127_0": {
      "nm": "Frozen pizza",
      "vw": 497.131
    },
    "127_1": {
      "nm": "Frozen pizza",
      "vw": 506.2045
    },
    "127_2": {
      "nm": "Frozen pizza",
      "vw": 507.9726
    },
    "127_3": {
      "nm": "Frozen pizza",
      "vw": 501.6383
    },
    "127_4": {
      "nm": "Frozen pizza",
      "vw": 520
    },
    "127_6": {
      "nm": "Frozen pizza",
      "vw": 500
    },
    "128_0": {
      "nm": "Pasta",
      "vw": 58.5282
    },
    "128_1": {
      "nm": "Pasta",
      "vw": 56.5
    },
    "128_2": {
      "nm": "Pasta",
      "vw": 82
    },
    "128_3": {
      "nm": "Pasta",
      "vw": 55
    },
    "128_4": {
      "nm": "Pasta",
      "vw": 95.1784
    },
    "128_5": {
      "nm": "Pasta",
      "vw": 94.0291
    },
    "128_6": {
      "nm": "Pasta",
      "vw": 103
    },
    "128_9": {
      "nm": "Pasta",
      "vw": 119.3911
    },
    "129_0": {
      "nm": "Hamburger",
      "vw": 2368.362
    },
    "129_1": {
      "nm": "Hamburger",
      "vw": 2342.3809
    },
    "129_11": {
      "nm": "Hamburger",
      "vw": 3500
    },
    "129_2": {
      "nm": "Hamburger",
      "vw": 2319.799
    },
    "129_3": {
      "nm": "Hamburger",
      "vw": 2681.2178
    },
    "129_4": {
      "nm": "Hamburger",
      "vw": 2759.6428
    },
    "129_5": {
      "nm": "Hamburger",
      "vw": 2969.503
    },
    "129_6": {
      "nm": "Hamburger",
      "vw": 3472.5745
    },
    "129_7": {
      "nm": "Hamburger",
      "vw": 3508.2222
    },
    "129_8": {
      "nm": "Hamburger",
      "vw": 3061.0652
    },
    "12_0": {
      "nm": "Diesel",
      "vw": 43.4511
    },
    "12_1": {
      "nm": "Diesel",
      "vw": 43.5217
    },
    "12_2": {
      "nm": "Diesel",
      "vw": 43.8358
    },
    "12_3": {
      "nm": "Diesel",
      "vw": 44.2602
    },
    "12_4": {
      "nm": "Diesel",
      "vw": 44.707
    },
    "12_5": {
      "nm": "Diesel",
      "vw": 45.0286
    },
    "12_6": {
      "nm": "Diesel",
      "vw": 44.123
    },
    "12_7": {
      "nm": "Diesel",
      "vw": 46.75
    },
    "130_0": {
      "nm": "Lasagna",
      "vw": 2335.5657
    },
    "130_1": {
      "nm": "Lasagna",
      "vw": 2340.6433
    },
    "130_10": {
      "nm": "Lasagna",
      "vw": 3337.907
    },
    "130_12": {
      "nm": "Lasagna",
      "vw": 3500
    },
    "130_2": {
      "nm": "Lasagna",
      "vw": 2502.2568
    },
    "130_3": {
      "nm": "Lasagna",
      "vw": 2662.285
    },
    "130_4": {
      "nm": "Lasagna",
      "vw": 2787.2124
    },
    "130_5": {
      "nm": "Lasagna",
      "vw": 2976.412
    },
    "130_6": {
      "nm": "Lasagna",
      "vw": 3090
    },
    "130_7": {
      "nm": "Lasagna",
      "vw": 3098.6956
    },
    "130_8": {
      "nm": "Lasagna",
      "vw": 3240
    },
    "130_9": {
      "nm": "Lasagna",
      "vw": 3250
    },
    "131_0": {
      "nm": "Meat balls",
      "vw": 2376.1982
    },
    "131_1": {
      "nm": "Meat balls",
      "vw": 2376.8882
    },
    "131_2": {
      "nm": "Meat balls",
      "vw": 2430.1943
    },
    "131_3": {
      "nm": "Meat balls",
      "vw": 2637.8513
    },
    "131_4": {
      "nm": "Meat balls",
      "vw": 2695
    },
    "131_5": {
      "nm": "Meat balls",
      "vw": 2921.4885
    },
    "131_6": {
      "nm": "Meat balls",
      "vw": 2960
    },
    "131_7": {
      "nm": "Meat balls",
      "vw": 3000
    },
    "131_8": {
      "nm": "Meat balls",
      "vw": 3040
    },
    "131_9": {
      "nm": "Meat balls",
      "vw": 3050
    },
    "132_0": {
      "nm": "Cocktails",
      "vw": 2388.5547
    },
    "132_1": {
      "nm": "Cocktails",
      "vw": 2392.9556
    },
    "132_10": {
      "nm": "Cocktails",
      "vw": 3900
    },
    "132_12": {
      "nm": "Cocktails",
      "vw": 4390
    },
    "132_2": {
      "nm": "Cocktails",
      "vw": 2605.7275
    },
    "132_3": {
      "nm": "Cocktails",
      "vw": 3420
    },
    "132_4": {
      "nm": "Cocktails",
      "vw": 3354.2856
    },
    "132_5": {
      "nm": "Cocktails",
      "vw": 3385.3274
    },
    "132_6": {
      "nm": "Cocktails",
      "vw": 3434.373
    },
    "132_7": {
      "nm": "Cocktails",
      "vw": 3443.6208
    },
    "132_8": {
      "nm": "Cocktails",
      "vw": 3449.0908
    },
    "132_9": {
      "nm": "Cocktails",
      "vw": 3490
    },
    "133_0": {
      "nm": "Flour",
      "vw": 17.7302
    },
    "133_1": {
      "nm": "Flour",
      "vw": 18.8596
    },
    "133_10": {
      "nm": "Flour",
      "vw": 47.75
    },
    "133_2": {
      "nm": "Flour",
      "vw": 21.6324
    },
    "133_3": {
      "nm": "Flour",
      "vw": 21.755
    },
    "133_4": {
      "nm": "Flour",
      "vw": 23.8595
    },
    "133_5": {
      "nm": "Flour",
      "vw": 24.0468
    },
    "133_6": {
      "nm": "Flour",
      "vw": 25.6214
    },
    "133_7": {
      "nm": "Flour",
      "vw": 28
    },
    "133_8": {
      "nm": "Flour",
      "vw": 30.5801
    },
    "133_9": {
      "nm": "Flour",
      "vw": 36
    },
    "134_0": {
      "nm": "Butter",
      "vw": 56.8536
    },
    "134_1": {
      "nm": "Butter",
      "vw": 57.2615
    },
    "134_10": {
      "nm": "Butter",
      "vw": 88.0437
    },
    "134_12": {
      "nm": "Butter",
      "vw": 93.8947
    },
    "134_2": {
      "nm": "Butter",
      "vw": 58.3918
    },
    "134_3": {
      "nm": "Butter",
      "vw": 59.345
    },
    "134_4": {
      "nm": "Butter",
      "vw": 65.1271
    },
    "134_5": {
      "nm": "Butter",
      "vw": 78.3797
    },
    "134_6": {
      "nm": "Butter",
      "vw": 78
    },
    "134_7": {
      "nm": "Butter",
      "vw": 84.4418
    },
    "134_8": {
      "nm": "Butter",
      "vw": 84.0049
    },
    "134_9": {
      "nm": "Butter",
      "vw": 88
    },
    "135_0": {
      "nm": "Sugar",
      "vw": 19.3872
    },
    "135_1": {
      "nm": "Sugar",
      "vw": 19.6436
    },
    "135_10": {
      "nm": "Sugar",
      "vw": 28
    },
    "135_11": {
      "nm": "Sugar",
      "vw": 36
    },
    "135_2": {
      "nm": "Sugar",
      "vw": 19.8202
    },
    "135_3": {
      "nm": "Sugar",
      "vw": 20.1525
    },
    "135_4": {
      "nm": "Sugar",
      "vw": 22.4071
    },
    "135_5": {
      "nm": "Sugar",
      "vw": 23.3126
    },
    "135_6": {
      "nm": "Sugar",
      "vw": 25.5
    },
    "135_7": {
      "nm": "Sugar",
      "vw": 27.4808
    },
    "135_8": {
      "nm": "Sugar",
      "vw": 32
    },
    "135_9": {
      "nm": "Sugar",
      "vw": 28
    },
    "136_0": {
      "nm": "Cocoa",
      "vw": 1.6286
    },
    "136_1": {
      "nm": "Cocoa",
      "vw": 1.9572
    },
    "136_2": {
      "nm": "Cocoa",
      "vw": 2.0024
    },
    "136_3": {
      "nm": "Cocoa",
      "vw": 2.144
    },
    "136_4": {
      "nm": "Cocoa",
      "vw": 2.4224
    },
    "136_5": {
      "nm": "Cocoa",
      "vw": 3.15
    },
    "137_0": {
      "nm": "Dough",
      "vw": 133.3443
    },
    "137_1": {
      "nm": "Dough",
      "vw": 134.6284
    },
    "137_2": {
      "nm": "Dough",
      "vw": 135.4546
    },
    "137_3": {
      "nm": "Dough",
      "vw": 150.8598
    },
    "137_4": {
      "nm": "Dough",
      "vw": 150
    },
    "137_5": {
      "nm": "Dough",
      "vw": 150.2777
    },
    "137_6": {
      "nm": "Dough",
      "vw": 149
    },
    "137_9": {
      "nm": "Dough",
      "vw": 140
    },
    "138_0": {
      "nm": "Sauce",
      "vw": 1341.16
    },
    "138_1": {
      "nm": "Sauce",
      "vw": 1361.5598
    },
    "138_2": {
      "nm": "Sauce",
      "vw": 1500
    },
    "138_3": {
      "nm": "Sauce",
      "vw": 1776.9775
    },
    "138_4": {
      "nm": "Sauce",
      "vw": 1625.8527
    },
    "138_5": {
      "nm": "Sauce",
      "vw": 1890
    },
    "138_6": {
      "nm": "Sauce",
      "vw": 1800
    },
    "139_0": {
      "nm": "Fodder",
      "vw": 11.633
    },
    "139_1": {
      "nm": "Fodder",
      "vw": 11.774
    },
    "139_11": {
      "nm": "Fodder",
      "vw": 24.875
    },
    "139_2": {
      "nm": "Fodder",
      "vw": 11.7747
    },
    "139_3": {
      "nm": "Fodder",
      "vw": 12.2898
    },
    "139_4": {
      "nm": "Fodder",
      "vw": 12.0934
    },
    "139_5": {
      "nm": "Fodder",
      "vw": 12.7768
    },
    "139_6": {
      "nm": "Fodder",
      "vw": 12.0935
    },
    "139_8": {
      "nm": "Fodder",
      "vw": 19.4502
    },
    "139_9": {
      "nm": "Fodder",
      "vw": 20.25
    },
    "13_0": {
      "nm": "Transport",
      "vw": 0.3937
    },
    "140_0": {
      "nm": "Chocolate",
      "vw": 258.0811
    },
    "140_1": {
      "nm": "Chocolate",
      "vw": 263.2189
    },
    "140_2": {
      "nm": "Chocolate",
      "vw": 264.8234
    },
    "140_3": {
      "nm": "Chocolate",
      "vw": 264.4172
    },
    "140_4": {
      "nm": "Chocolate",
      "vw": 266.1532
    },
    "140_5": {
      "nm": "Chocolate",
      "vw": 272
    },
    "141_0": {
      "nm": "Vegetable oil",
      "vw": 37.354
    },
    "141_1": {
      "nm": "Vegetable oil",
      "vw": 42.495
    },
    "141_10": {
      "nm": "Vegetable oil",
      "vw": 110
    },
    "141_11": {
      "nm": "Vegetable oil",
      "vw": 120
    },
    "141_2": {
      "nm": "Vegetable oil",
      "vw": 48.7107
    },
    "141_3": {
      "nm": "Vegetable oil",
      "vw": 55.3267
    },
    "141_4": {
      "nm": "Vegetable oil",
      "vw": 58.7599
    },
    "141_5": {
      "nm": "Vegetable oil",
      "vw": 63
    },
    "141_6": {
      "nm": "Vegetable oil",
      "vw": 63.5627
    },
    "141_7": {
      "nm": "Vegetable oil",
      "vw": 65.3374
    },
    "141_8": {
      "nm": "Vegetable oil",
      "vw": 69.4934
    },
    "141_9": {
      "nm": "Vegetable oil",
      "vw": 97
    },
    "142_0": {
      "nm": "Salad",
      "vw": 829.8611
    },
    "142_1": {
      "nm": "Salad",
      "vw": 821.282
    },
    "142_10": {
      "nm": "Salad",
      "vw": 1198.992
    },
    "142_11": {
      "nm": "Salad",
      "vw": 1470
    },
    "142_12": {
      "nm": "Salad",
      "vw": 1472.3405
    },
    "142_2": {
      "nm": "Salad",
      "vw": 836.4282
    },
    "142_3": {
      "nm": "Salad",
      "vw": 885.0891
    },
    "142_4": {
      "nm": "Salad",
      "vw": 913.3903
    },
    "142_5": {
      "nm": "Salad",
      "vw": 954.2236
    },
    "142_6": {
      "nm": "Salad",
      "vw": 1004.7449
    },
    "142_7": {
      "nm": "Salad",
      "vw": 1132.1621
    },
    "142_8": {
      "nm": "Salad",
      "vw": 1120
    },
    "142_9": {
      "nm": "Salad",
      "vw": 1270
    },
    "143_0": {
      "nm": "Samosa",
      "vw": 734.6744
    },
    "143_1": {
      "nm": "Samosa",
      "vw": 794.5048
    },
    "143_10": {
      "nm": "Samosa",
      "vw": 1280
    },
    "143_11": {
      "nm": "Samosa",
      "vw": 1290
    },
    "143_12": {
      "nm": "Samosa",
      "vw": 1433.9332
    },
    "143_2": {
      "nm": "Samosa",
      "vw": 798.6885
    },
    "143_3": {
      "nm": "Samosa",
      "vw": 804.4924
    },
    "143_4": {
      "nm": "Samosa",
      "vw": 833.9196
    },
    "143_5": {
      "nm": "Samosa",
      "vw": 871.467
    },
    "143_6": {
      "nm": "Samosa",
      "vw": 898.4965
    },
    "143_7": {
      "nm": "Samosa",
      "vw": 900.0153
    },
    "143_8": {
      "nm": "Samosa",
      "vw": 1070
    },
    "143_9": {
      "nm": "Samosa",
      "vw": 1043.369
    },
    "144_0": {
      "nm": "Xmas ornament",
      "vw": 18.1706
    },
    "144_2": {
      "nm": "Xmas ornament",
      "vw": 18.3981
    },
    "144_3": {
      "nm": "Xmas ornament",
      "vw": 18.9
    },
    "144_4": {
      "nm": "Xmas ornament",
      "vw": 19.5
    },
    "145_0": {
      "nm": "Recipes",
      "vw": 141.2504
    },
    "146_0": {
      "nm": "Pumpkin",
      "vw": 12.2849
    },
    "146_1": {
      "nm": "Pumpkin",
      "vw": 12.5
    },
    "146_2": {
      "nm": "Pumpkin",
      "vw": 12.2879
    },
    "146_3": {
      "nm": "Pumpkin",
      "vw": 12.4103
    },
    "146_4": {
      "nm": "Pumpkin",
      "vw": 13
    },
    "146_5": {
      "nm": "Pumpkin",
      "vw": 12.3
    },
    "146_6": {
      "nm": "Pumpkin",
      "vw": 13.5
    },
    "146_7": {
      "nm": "Pumpkin",
      "vw": 13.6
    },
    "147_0": {
      "nm": "Jack o'lantern",
      "vw": 46.4999
    },
    "147_1": {
      "nm": "Jack o'lantern",
      "vw": 47.4525
    },
    "147_2": {
      "nm": "Jack o'lantern",
      "vw": 45
    },
    "148_0": {
      "nm": "Witch costume",
      "vw": 35.1916
    },
    "148_1": {
      "nm": "Witch costume",
      "vw": 35.2062
    },
    "148_2": {
      "nm": "Witch costume",
      "vw": 36.3197
    },
    "148_3": {
      "nm": "Witch costume",
      "vw": 34.75
    },
    "148_4": {
      "nm": "Witch costume",
      "vw": 37
    },
    "148_5": {
      "nm": "Witch costume",
      "vw": 44.75
    },
    "148_7": {
      "nm": "Witch costume",
      "vw": 58
    },
    "149_0": {
      "nm": "Pumpkin soup",
      "vw": 900.9722
    },
    "149_1": {
      "nm": "Pumpkin soup",
      "vw": 900
    },
    "149_10": {
      "nm": "Pumpkin soup",
      "vw": 1859.531
    },
    "149_11": {
      "nm": "Pumpkin soup",
      "vw": 2017.25
    },
    "149_2": {
      "nm": "Pumpkin soup",
      "vw": 895
    },
    "149_3": {
      "nm": "Pumpkin soup",
      "vw": 990
    },
    "149_4": {
      "nm": "Pumpkin soup",
      "vw": 953.8627
    },
    "149_5": {
      "nm": "Pumpkin soup",
      "vw": 999.3938
    },
    "149_6": {
      "nm": "Pumpkin soup",
      "vw": 1280
    },
    "149_7": {
      "nm": "Pumpkin soup",
      "vw": 1280
    },
    "149_8": {
      "nm": "Pumpkin soup",
      "vw": 1287.0588
    },
    "149_9": {
      "nm": "Pumpkin soup",
      "vw": 1450
    },
    "14_0": {
      "nm": "Minerals",
      "vw": 11.9988
    },
    "14_1": {
      "nm": "Minerals",
      "vw": 12.1632
    },
    "14_10": {
      "nm": "Minerals",
      "vw": 12.4
    },
    "14_12": {
      "nm": "Minerals",
      "vw": 12.3
    },
    "14_2": {
      "nm": "Minerals",
      "vw": 12.2055
    },
    "14_3": {
      "nm": "Minerals",
      "vw": 12.3036
    },
    "14_4": {
      "nm": "Minerals",
      "vw": 12.2961
    },
    "14_5": {
      "nm": "Minerals",
      "vw": 12.3803
    },
    "14_6": {
      "nm": "Minerals",
      "vw": 12.3793
    },
    "14_7": {
      "nm": "Minerals",
      "vw": 12.4994
    },
    "14_8": {
      "nm": "Minerals",
      "vw": 12.4
    },
    "150_0": {
      "nm": "Tree",
      "vw": 331.0367
    },
    "150_1": {
      "nm": "Tree",
      "vw": 845.2437
    },
    "150_10": {
      "nm": "Tree",
      "vw": 328763.16
    },
    "150_11": {
      "nm": "Tree",
      "vw": 638000
    },
    "150_12": {
      "nm": "Tree",
      "vw": 1360357.1
    },
    "150_2": {
      "nm": "Tree",
      "vw": 1822.7587
    },
    "150_3": {
      "nm": "Tree",
      "vw": 2728.2292
    },
    "150_4": {
      "nm": "Tree",
      "vw": 5230.755
    },
    "150_5": {
      "nm": "Tree",
      "vw": 7987.75
    },
    "150_6": {
      "nm": "Tree",
      "vw": 17837.451
    },
    "150_7": {
      "nm": "Tree",
      "vw": 41312.5
    },
    "150_8": {
      "nm": "Tree",
      "vw": 64133.332
    },
    "150_9": {
      "nm": "Tree",
      "vw": 159985.72
    },
    "151_0": {
      "nm": "Easter Bunny",
      "vw": 242.6533
    },
    "151_1": {
      "nm": "Easter Bunny",
      "vw": 254
    },
    "151_2": {
      "nm": "Easter Bunny",
      "vw": 254
    },
    "152_0": {
      "nm": "Ramadan sweets",
      "vw": 226
    },
    "152_2": {
      "nm": "Ramadan sweets",
      "vw": 230
    },
    "153_0": {
      "nm": "Chocolate icecream",
      "vw": 75.8946
    },
    "153_1": {
      "nm": "Chocolate icecream",
      "vw": 55.4864
    },
    "153_2": {
      "nm": "Chocolate icecream",
      "vw": 84.5618
    },
    "153_3": {
      "nm": "Chocolate icecream",
      "vw": 60
    },
    "153_4": {
      "nm": "Chocolate icecream",
      "vw": 86.2313
    },
    "153_8": {
      "nm": "Chocolate icecream",
      "vw": 80
    },
    "154_0": {
      "nm": "Apple icecream",
      "vw": 86.0581
    },
    "154_1": {
      "nm": "Apple icecream",
      "vw": 81.1501
    },
    "154_2": {
      "nm": "Apple icecream",
      "vw": 79.661
    },
    "154_3": {
      "nm": "Apple icecream",
      "vw": 85.404
    },
    "154_4": {
      "nm": "Apple icecream",
      "vw": 69.9784
    },
    "154_9": {
      "nm": "Apple icecream",
      "vw": 60
    },
    "155_0": {
      "nm": "Cream egg",
      "vw": 134.8613
    },
    "155_1": {
      "nm": "Cream egg",
      "vw": 140
    },
    "155_10": {
      "nm": "Cream egg",
      "vw": 200
    },
    "155_2": {
      "nm": "Cream egg",
      "vw": 140
    },
    "155_3": {
      "nm": "Cream egg",
      "vw": 141
    },
    "155_4": {
      "nm": "Cream egg",
      "vw": 142
    },
    "15_0": {
      "nm": "Bauxite",
      "vw": 10.93
    },
    "15_1": {
      "nm": "Bauxite",
      "vw": 11.0051
    },
    "15_10": {
      "nm": "Bauxite",
      "vw": 11.4
    },
    "15_2": {
      "nm": "Bauxite",
      "vw": 11.1203
    },
    "15_3": {
      "nm": "Bauxite",
      "vw": 11.2501
    },
    "15_4": {
      "nm": "Bauxite",
      "vw": 11.3584
    },
    "15_5": {
      "nm": "Bauxite",
      "vw": 11.2066
    },
    "15_6": {
      "nm": "Bauxite",
      "vw": 11.3476
    },
    "15_7": {
      "nm": "Bauxite",
      "vw": 11.5
    },
    "16_0": {
      "nm": "Silicon",
      "vw": 8.4886
    },
    "16_1": {
      "nm": "Silicon",
      "vw": 8.7458
    },
    "16_10": {
      "nm": "Silicon",
      "vw": 9.6
    },
    "16_11": {
      "nm": "Silicon",
      "vw": 9.5
    },
    "16_12": {
      "nm": "Silicon",
      "vw": 9.5677
    },
    "16_2": {
      "nm": "Silicon",
      "vw": 8.7681
    },
    "16_3": {
      "nm": "Silicon",
      "vw": 8.8934
    },
    "16_4": {
      "nm": "Silicon",
      "vw": 9.0713
    },
    "16_5": {
      "nm": "Silicon",
      "vw": 9.2142
    },
    "16_6": {
      "nm": "Silicon",
      "vw": 8.8623
    },
    "16_7": {
      "nm": "Silicon",
      "vw": 9.4322
    },
    "16_9": {
      "nm": "Silicon",
      "vw": 9.0264
    },
    "17_0": {
      "nm": "Chemicals",
      "vw": 15.7649
    },
    "17_1": {
      "nm": "Chemicals",
      "vw": 15.8439
    },
    "17_10": {
      "nm": "Chemicals",
      "vw": 19.0966
    },
    "17_12": {
      "nm": "Chemicals",
      "vw": 17.45
    },
    "17_2": {
      "nm": "Chemicals",
      "vw": 16.0079
    },
    "17_3": {
      "nm": "Chemicals",
      "vw": 16.0977
    },
    "17_4": {
      "nm": "Chemicals",
      "vw": 16.144
    },
    "17_5": {
      "nm": "Chemicals",
      "vw": 16.324
    },
    "17_6": {
      "nm": "Chemicals",
      "vw": 16.3295
    },
    "17_7": {
      "nm": "Chemicals",
      "vw": 16.4829
    },
    "17_8": {
      "nm": "Chemicals",
      "vw": 17
    },
    "17_9": {
      "nm": "Chemicals",
      "vw": 17.7587
    },
    "18_0": {
      "nm": "Aluminium",
      "vw": 21.0536
    },
    "18_1": {
      "nm": "Aluminium",
      "vw": 21.4284
    },
    "18_10": {
      "nm": "Aluminium",
      "vw": 27
    },
    "18_2": {
      "nm": "Aluminium",
      "vw": 21.583
    },
    "18_3": {
      "nm": "Aluminium",
      "vw": 22.2464
    },
    "18_4": {
      "nm": "Aluminium",
      "vw": 22.4341
    },
    "18_5": {
      "nm": "Aluminium",
      "vw": 23.8266
    },
    "18_6": {
      "nm": "Aluminium",
      "vw": 25.2409
    },
    "18_8": {
      "nm": "Aluminium",
      "vw": 25.6055
    },
    "19_0": {
      "nm": "Plastic",
      "vw": 12.6631
    },
    "19_1": {
      "nm": "Plastic",
      "vw": 12.8747
    },
    "19_10": {
      "nm": "Plastic",
      "vw": 15.2
    },
    "19_2": {
      "nm": "Plastic",
      "vw": 13.1033
    },
    "19_3": {
      "nm": "Plastic",
      "vw": 13.2693
    },
    "19_4": {
      "nm": "Plastic",
      "vw": 13.4958
    },
    "19_5": {
      "nm": "Plastic",
      "vw": 13.5903
    },
    "19_6": {
      "nm": "Plastic",
      "vw": 13.7841
    },
    "19_7": {
      "nm": "Plastic",
      "vw": 14
    },
    "19_8": {
      "nm": "Plastic",
      "vw": 16.5
    },
    "19_9": {
      "nm": "Plastic",
      "vw": 15.8
    },
    "1_0": {
      "nm": "Power",
      "vw": 0.2719
    },
    "1_1": {
      "nm": "Power",
      "vw": 0.2752
    },
    "1_10": {
      "nm": "Power",
      "vw": 0.2814
    },
    "1_11": {
      "nm": "Power",
      "vw": 0.2834
    },
    "1_12": {
      "nm": "Power",
      "vw": 0.2849
    },
    "1_2": {
      "nm": "Power",
      "vw": 0.2756
    },
    "1_3": {
      "nm": "Power",
      "vw": 0.2766
    },
    "1_4": {
      "nm": "Power",
      "vw": 0.2782
    },
    "1_5": {
      "nm": "Power",
      "vw": 0.2783
    },
    "1_6": {
      "nm": "Power",
      "vw": 0.2776
    },
    "1_7": {
      "nm": "Power",
      "vw": 0.2787
    },
    "1_8": {
      "nm": "Power",
      "vw": 0.2813
    },
    "1_9": {
      "nm": "Power",
      "vw": 0.2805
    },
    "20_0": {
      "nm": "Processors",
      "vw": 118.8226
    },
    "20_1": {
      "nm": "Processors",
      "vw": 120.8959
    },
    "20_10": {
      "nm": "Processors",
      "vw": 158
    },
    "20_12": {
      "nm": "Processors",
      "vw": 180
    },
    "20_2": {
      "nm": "Processors",
      "vw": 123.633
    },
    "20_3": {
      "nm": "Processors",
      "vw": 125.0678
    },
    "20_4": {
      "nm": "Processors",
      "vw": 132.7812
    },
    "20_5": {
      "nm": "Processors",
      "vw": 137.8294
    },
    "20_6": {
      "nm": "Processors",
      "vw": 138.2861
    },
    "20_7": {
      "nm": "Processors",
      "vw": 138
    },
    "20_8": {
      "nm": "Processors",
      "vw": 150
    },
    "21_0": {
      "nm": "Electronic components",
      "vw": 58.6553
    },
    "21_1": {
      "nm": "Electronic components",
      "vw": 59.1132
    },
    "21_10": {
      "nm": "Electronic components",
      "vw": 133.736
    },
    "21_2": {
      "nm": "Electronic components",
      "vw": 59.4808
    },
    "21_3": {
      "nm": "Electronic components",
      "vw": 59.8386
    },
    "21_4": {
      "nm": "Electronic components",
      "vw": 61.9919
    },
    "21_5": {
      "nm": "Electronic components",
      "vw": 63.4536
    },
    "21_6": {
      "nm": "Electronic components",
      "vw": 65.0017
    },
    "21_7": {
      "nm": "Electronic components",
      "vw": 66.5
    },
    "22_0": {
      "nm": "Batteries",
      "vw": 91.3419
    },
    "22_1": {
      "nm": "Batteries",
      "vw": 92.6288
    },
    "22_11": {
      "nm": "Batteries",
      "vw": 112
    },
    "22_2": {
      "nm": "Batteries",
      "vw": 92.5285
    },
    "22_3": {
      "nm": "Batteries",
      "vw": 92.7871
    },
    "22_4": {
      "nm": "Batteries",
      "vw": 93.2051
    },
    "22_5": {
      "nm": "Batteries",
      "vw": 93.7327
    },
    "22_6": {
      "nm": "Batteries",
      "vw": 94.0676
    },
    "22_7": {
      "nm": "Batteries",
      "vw": 94.2244
    },
    "22_8": {
      "nm": "Batteries",
      "vw": 95.1221
    },
    "22_9": {
      "nm": "Batteries",
      "vw": 94
    },
    "23_0": {
      "nm": "Displays",
      "vw": 129.6532
    },
    "23_1": {
      "nm": "Displays",
      "vw": 132.0466
    },
    "23_10": {
      "nm": "Displays",
      "vw": 150
    },
    "23_11": {
      "nm": "Displays",
      "vw": 146
    },
    "23_2": {
      "nm": "Displays",
      "vw": 132.2015
    },
    "23_3": {
      "nm": "Displays",
      "vw": 133.8232
    },
    "23_4": {
      "nm": "Displays",
      "vw": 136.9497
    },
    "23_5": {
      "nm": "Displays",
      "vw": 139.2654
    },
    "23_6": {
      "nm": "Displays",
      "vw": 138.2983
    },
    "23_7": {
      "nm": "Displays",
      "vw": 143.2855
    },
    "23_8": {
      "nm": "Displays",
      "vw": 141.5855
    },
    "24_0": {
      "nm": "Smart phones",
      "vw": 642.904
    },
    "24_1": {
      "nm": "Smart phones",
      "vw": 648.42
    },
    "24_2": {
      "nm": "Smart phones",
      "vw": 642.5542
    },
    "24_3": {
      "nm": "Smart phones",
      "vw": 655.4321
    },
    "24_4": {
      "nm": "Smart phones",
      "vw": 660.4436
    },
    "24_5": {
      "nm": "Smart phones",
      "vw": 666.1383
    },
    "24_6": {
      "nm": "Smart phones",
      "vw": 680.5743
    },
    "24_7": {
      "nm": "Smart phones",
      "vw": 684.4014
    },
    "24_8": {
      "nm": "Smart phones",
      "vw": 700
    },
    "25_0": {
      "nm": "Tablets",
      "vw": 805.5586
    },
    "25_1": {
      "nm": "Tablets",
      "vw": 809.5395
    },
    "25_2": {
      "nm": "Tablets",
      "vw": 796.2581
    },
    "25_3": {
      "nm": "Tablets",
      "vw": 818.1491
    },
    "25_4": {
      "nm": "Tablets",
      "vw": 825.4157
    },
    "25_5": {
      "nm": "Tablets",
      "vw": 842.0637
    },
    "25_6": {
      "nm": "Tablets",
      "vw": 857.7483
    },
    "25_7": {
      "nm": "Tablets",
      "vw": 855.3226
    },
    "25_8": {
      "nm": "Tablets",
      "vw": 950
    },
    "25_9": {
      "nm": "Tablets",
      "vw": 1000
    },
    "26_0": {
      "nm": "Laptops",
      "vw": 1277.4202
    },
    "26_1": {
      "nm": "Laptops",
      "vw": 1254.9789
    },
    "26_10": {
      "nm": "Laptops",
      "vw": 2100
    },
    "26_2": {
      "nm": "Laptops",
      "vw": 1284.6904
    },
    "26_3": {
      "nm": "Laptops",
      "vw": 1296.5068
    },
    "26_4": {
      "nm": "Laptops",
      "vw": 1334.2582
    },
    "26_5": {
      "nm": "Laptops",
      "vw": 1352.2725
    },
    "26_6": {
      "nm": "Laptops",
      "vw": 1440
    },
    "26_7": {
      "nm": "Laptops",
      "vw": 1450
    },
    "27_0": {
      "nm": "Monitors",
      "vw": 591.7982
    },
    "27_1": {
      "nm": "Monitors",
      "vw": 604.3455
    },
    "27_2": {
      "nm": "Monitors",
      "vw": 610
    },
    "27_3": {
      "nm": "Monitors",
      "vw": 613.9925
    },
    "27_4": {
      "nm": "Monitors",
      "vw": 626.0175
    },
    "27_5": {
      "nm": "Monitors",
      "vw": 637.7113
    },
    "27_6": {
      "nm": "Monitors",
      "vw": 650
    },
    "27_7": {
      "nm": "Monitors",
      "vw": 640
    },
    "28_0": {
      "nm": "Televisions",
      "vw": 992.6899
    },
    "28_1": {
      "nm": "Televisions",
      "vw": 999.931
    },
    "28_2": {
      "nm": "Televisions",
      "vw": 1013.6478
    },
    "28_3": {
      "nm": "Televisions",
      "vw": 1029.9263
    },
    "28_4": {
      "nm": "Televisions",
      "vw": 1032.4548
    },
    "28_5": {
      "nm": "Televisions",
      "vw": 1039.3143
    },
    "28_6": {
      "nm": "Televisions",
      "vw": 1057.714
    },
    "28_8": {
      "nm": "Televisions",
      "vw": 1100
    },
    "29_0": {
      "nm": "Plant research",
      "vw": 116.3896
    },
    "2_0": {
      "nm": "Water",
      "vw": 0.3873
    },
    "2_1": {
      "nm": "Water",
      "vw": 0.3909
    },
    "2_10": {
      "nm": "Water",
      "vw": 0.4936
    },
    "2_11": {
      "nm": "Water",
      "vw": 0.54
    },
    "2_12": {
      "nm": "Water",
      "vw": 0.6455
    },
    "2_2": {
      "nm": "Water",
      "vw": 0.3936
    },
    "2_3": {
      "nm": "Water",
      "vw": 0.4045
    },
    "2_4": {
      "nm": "Water",
      "vw": 0.4121
    },
    "2_5": {
      "nm": "Water",
      "vw": 0.4518
    },
    "2_6": {
      "nm": "Water",
      "vw": 0.4558
    },
    "2_7": {
      "nm": "Water",
      "vw": 0.4822
    },
    "2_8": {
      "nm": "Water",
      "vw": 0.4904
    },
    "2_9": {
      "nm": "Water",
      "vw": 0.4897
    },
    "30_0": {
      "nm": "Energy research",
      "vw": 173.6172
    },
    "31_0": {
      "nm": "Mining research",
      "vw": 194.9817
    },
    "32_0": {
      "nm": "Electronics research",
      "vw": 238.3211
    },
    "33_0": {
      "nm": "Breeding research",
      "vw": 126.2903
    },
    "34_0": {
      "nm": "Chemistry research",
      "vw": 100.0163
    },
    "35_0": {
      "nm": "Software",
      "vw": 99.8216
    },
    "3_0": {
      "nm": "Apples",
      "vw": 2.6455
    },
    "3_1": {
      "nm": "Apples",
      "vw": 2.7642
    },
    "3_11": {
      "nm": "Apples",
      "vw": 5.2
    },
    "3_2": {
      "nm": "Apples",
      "vw": 2.8418
    },
    "3_3": {
      "nm": "Apples",
      "vw": 2.9294
    },
    "3_4": {
      "nm": "Apples",
      "vw": 3.084
    },
    "3_5": {
      "nm": "Apples",
      "vw": 3.3361
    },
    "3_6": {
      "nm": "Apples",
      "vw": 3.4696
    },
    "3_7": {
      "nm": "Apples",
      "vw": 3.95
    },
    "3_8": {
      "nm": "Apples",
      "vw": 4.5
    },
    "40_0": {
      "nm": "Cotton",
      "vw": 1.5192
    },
    "40_1": {
      "nm": "Cotton",
      "vw": 1.554
    },
    "40_2": {
      "nm": "Cotton",
      "vw": 1.6298
    },
    "40_3": {
      "nm": "Cotton",
      "vw": 1.7026
    },
    "40_4": {
      "nm": "Cotton",
      "vw": 1.7012
    },
    "40_5": {
      "nm": "Cotton",
      "vw": 1.7671
    },
    "40_6": {
      "nm": "Cotton",
      "vw": 1.89
    },
    "40_7": {
      "nm": "Cotton",
      "vw": 1.95
    },
    "41_0": {
      "nm": "Fabric",
      "vw": 4.5291
    },
    "41_1": {
      "nm": "Fabric",
      "vw": 4.5696
    },
    "41_10": {
      "nm": "Fabric",
      "vw": 9.5
    },
    "41_11": {
      "nm": "Fabric",
      "vw": 10.5
    },
    "41_2": {
      "nm": "Fabric",
      "vw": 4.6539
    },
    "41_3": {
      "nm": "Fabric",
      "vw": 4.7865
    },
    "41_4": {
      "nm": "Fabric",
      "vw": 5.1638
    },
    "41_5": {
      "nm": "Fabric",
      "vw": 5.4697
    },
    "41_6": {
      "nm": "Fabric",
      "vw": 5.7
    },
    "41_7": {
      "nm": "Fabric",
      "vw": 5.9
    },
    "41_8": {
      "nm": "Fabric",
      "vw": 5.5
    },
    "41_9": {
      "nm": "Fabric",
      "vw": 9.4
    },
    "42_0": {
      "nm": "Iron ore",
      "vw": 5.1139
    },
    "42_1": {
      "nm": "Iron ore",
      "vw": 5.1484
    },
    "42_2": {
      "nm": "Iron ore",
      "vw": 5.1665
    },
    "42_3": {
      "nm": "Iron ore",
      "vw": 5.2408
    },
    "42_4": {
      "nm": "Iron ore",
      "vw": 5.3145
    },
    "42_5": {
      "nm": "Iron ore",
      "vw": 5.3
    },
    "42_6": {
      "nm": "Iron ore",
      "vw": 5.4
    },
    "42_7": {
      "nm": "Iron ore",
      "vw": 5.3
    },
    "43_0": {
      "nm": "Steel",
      "vw": 12.044
    },
    "43_1": {
      "nm": "Steel",
      "vw": 12.2383
    },
    "43_2": {
      "nm": "Steel",
      "vw": 12.3234
    },
    "43_3": {
      "nm": "Steel",
      "vw": 12.4149
    },
    "43_4": {
      "nm": "Steel",
      "vw": 12.4508
    },
    "43_5": {
      "nm": "Steel",
      "vw": 12.5928
    },
    "43_6": {
      "nm": "Steel",
      "vw": 12.8507
    },
    "43_7": {
      "nm": "Steel",
      "vw": 16.1
    },
    "43_8": {
      "nm": "Steel",
      "vw": 16.2
    },
    "44_0": {
      "nm": "Sand",
      "vw": 1.366
    },
    "44_1": {
      "nm": "Sand",
      "vw": 1.4127
    },
    "44_2": {
      "nm": "Sand",
      "vw": 1.4127
    },
    "44_3": {
      "nm": "Sand",
      "vw": 1.4123
    },
    "44_4": {
      "nm": "Sand",
      "vw": 1.4134
    },
    "44_5": {
      "nm": "Sand",
      "vw": 1.4784
    },
    "44_6": {
      "nm": "Sand",
      "vw": 1.4807
    },
    "44_7": {
      "nm": "Sand",
      "vw": 1.89
    },
    "45_0": {
      "nm": "Glass",
      "vw": 14.603
    },
    "45_1": {
      "nm": "Glass",
      "vw": 14.6499
    },
    "45_12": {
      "nm": "Glass",
      "vw": 15.8976
    },
    "45_2": {
      "nm": "Glass",
      "vw": 14.8085
    },
    "45_3": {
      "nm": "Glass",
      "vw": 14.8374
    },
    "45_4": {
      "nm": "Glass",
      "vw": 14.9565
    },
    "45_5": {
      "nm": "Glass",
      "vw": 15.0688
    },
    "45_7": {
      "nm": "Glass",
      "vw": 14.9975
    },
    "46_0": {
      "nm": "Leather",
      "vw": 27.7724
    },
    "46_1": {
      "nm": "Leather",
      "vw": 28.3808
    },
    "46_2": {
      "nm": "Leather",
      "vw": 29.6851
    },
    "46_3": {
      "nm": "Leather",
      "vw": 30.2037
    },
    "46_4": {
      "nm": "Leather",
      "vw": 30.2139
    },
    "46_5": {
      "nm": "Leather",
      "vw": 31.1043
    },
    "46_6": {
      "nm": "Leather",
      "vw": 32.2953
    },
    "46_7": {
      "nm": "Leather",
      "vw": 32.7282
    },
    "46_8": {
      "nm": "Leather",
      "vw": 34.22
    },
    "47_0": {
      "nm": "On-board computer",
      "vw": 489.0641
    },
    "47_1": {
      "nm": "On-board computer",
      "vw": 497.1277
    },
    "47_2": {
      "nm": "On-board computer",
      "vw": 500.9023
    },
    "47_3": {
      "nm": "On-board computer",
      "vw": 503.3772
    },
    "47_4": {
      "nm": "On-board computer",
      "vw": 507.502
    },
    "47_5": {
      "nm": "On-board computer",
      "vw": 510.6468
    },
    "47_6": {
      "nm": "On-board computer",
      "vw": 534.3769
    },
    "47_7": {
      "nm": "On-board computer",
      "vw": 501.6996
    },
    "47_8": {
      "nm": "On-board computer",
      "vw": 550
    },
    "48_0": {
      "nm": "Electric motor",
      "vw": 236.7051
    },
    "48_1": {
      "nm": "Electric motor",
      "vw": 242.1036
    },
    "48_10": {
      "nm": "Electric motor",
      "vw": 350
    },
    "48_2": {
      "nm": "Electric motor",
      "vw": 246.6715
    },
    "48_3": {
      "nm": "Electric motor",
      "vw": 251.7018
    },
    "48_4": {
      "nm": "Electric motor",
      "vw": 249.6342
    },
    "48_5": {
      "nm": "Electric motor",
      "vw": 253.7534
    },
    "48_7": {
      "nm": "Electric motor",
      "vw": 292
    },
    "48_8": {
      "nm": "Electric motor",
      "vw": 249.7562
    },
    "49_0": {
      "nm": "Luxury car interior",
      "vw": 990.5818
    },
    "49_1": {
      "nm": "Luxury car interior",
      "vw": 996.6667
    },
    "49_2": {
      "nm": "Luxury car interior",
      "vw": 1013.0023
    },
    "49_3": {
      "nm": "Luxury car interior",
      "vw": 1041.579
    },
    "49_4": {
      "nm": "Luxury car interior",
      "vw": 1072.8081
    },
    "49_5": {
      "nm": "Luxury car interior",
      "vw": 1180.364
    },
    "49_6": {
      "nm": "Luxury car interior",
      "vw": 1180
    },
    "49_7": {
      "nm": "Luxury car interior",
      "vw": 1150
    },
    "4_0": {
      "nm": "Oranges",
      "vw": 2.8137
    },
    "4_1": {
      "nm": "Oranges",
      "vw": 2.8951
    },
    "4_11": {
      "nm": "Oranges",
      "vw": 9
    },
    "4_2": {
      "nm": "Oranges",
      "vw": 3.0474
    },
    "4_3": {
      "nm": "Oranges",
      "vw": 3.1621
    },
    "4_4": {
      "nm": "Oranges",
      "vw": 3.2663
    },
    "4_5": {
      "nm": "Oranges",
      "vw": 3.2844
    },
    "4_6": {
      "nm": "Oranges",
      "vw": 3.427
    },
    "4_8": {
      "nm": "Oranges",
      "vw": 4.3
    },
    "50_0": {
      "nm": "Basic interior",
      "vw": 350.2583
    },
    "50_1": {
      "nm": "Basic interior",
      "vw": 353.7702
    },
    "50_10": {
      "nm": "Basic interior",
      "vw": 430
    },
    "50_2": {
      "nm": "Basic interior",
      "vw": 359.0859
    },
    "50_3": {
      "nm": "Basic interior",
      "vw": 362.1197
    },
    "50_4": {
      "nm": "Basic interior",
      "vw": 362.8855
    },
    "50_5": {
      "nm": "Basic interior",
      "vw": 360.7255
    },
    "50_6": {
      "nm": "Basic interior",
      "vw": 361.5425
    },
    "50_7": {
      "nm": "Basic interior",
      "vw": 378.6548
    },
    "51_0": {
      "nm": "Car body",
      "vw": 819.0175
    },
    "51_1": {
      "nm": "Car body",
      "vw": 829.2083
    },
    "51_2": {
      "nm": "Car body",
      "vw": 829.7331
    },
    "51_3": {
      "nm": "Car body",
      "vw": 886.4653
    },
    "51_4": {
      "nm": "Car body",
      "vw": 896.71
    },
    "51_5": {
      "nm": "Car body",
      "vw": 930
    },
    "51_6": {
      "nm": "Car body",
      "vw": 935.522
    },
    "51_7": {
      "nm": "Car body",
      "vw": 950
    },
    "51_8": {
      "nm": "Car body",
      "vw": 950
    },
    "52_0": {
      "nm": "Combustion engine",
      "vw": 660.0079
    },
    "52_1": {
      "nm": "Combustion engine",
      "vw": 660.628
    },
    "52_10": {
      "nm": "Combustion engine",
      "vw": 987.4636
    },
    "52_11": {
      "nm": "Combustion engine",
      "vw": 950
    },
    "52_2": {
      "nm": "Combustion engine",
      "vw": 670.1268
    },
    "52_3": {
      "nm": "Combustion engine",
      "vw": 677.6968
    },
    "52_4": {
      "nm": "Combustion engine",
      "vw": 681.1281
    },
    "52_5": {
      "nm": "Combustion engine",
      "vw": 691.1359
    },
    "52_6": {
      "nm": "Combustion engine",
      "vw": 724.9507
    },
    "52_7": {
      "nm": "Combustion engine",
      "vw": 970
    },
    "52_8": {
      "nm": "Combustion engine",
      "vw": 990
    },
    "53_0": {
      "nm": "Economy e-car",
      "vw": 3554.9297
    },
    "53_1": {
      "nm": "Economy e-car",
      "vw": 3537.5
    },
    "53_2": {
      "nm": "Economy e-car",
      "vw": 3663.0588
    },
    "53_3": {
      "nm": "Economy e-car",
      "vw": 3720
    },
    "53_4": {
      "nm": "Economy e-car",
      "vw": 3728.125
    },
    "53_5": {
      "nm": "Economy e-car",
      "vw": 3860
    },
    "53_6": {
      "nm": "Economy e-car",
      "vw": 3863.3333
    },
    "53_8": {
      "nm": "Economy e-car",
      "vw": 3990
    },
    "54_0": {
      "nm": "Luxury e-car",
      "vw": 6770.421
    },
    "54_1": {
      "nm": "Luxury e-car",
      "vw": 6738.3623
    },
    "54_2": {
      "nm": "Luxury e-car",
      "vw": 6721.1963
    },
    "54_3": {
      "nm": "Luxury e-car",
      "vw": 6768.0586
    },
    "54_4": {
      "nm": "Luxury e-car",
      "vw": 6991.6665
    },
    "54_5": {
      "nm": "Luxury e-car",
      "vw": 7009.406
    },
    "54_6": {
      "nm": "Luxury e-car",
      "vw": 7113.746
    },
    "54_7": {
      "nm": "Luxury e-car",
      "vw": 7381.25
    },
    "54_8": {
      "nm": "Luxury e-car",
      "vw": 7650
    },
    "55_0": {
      "nm": "Economy car",
      "vw": 2398.6633
    },
    "55_1": {
      "nm": "Economy car",
      "vw": 2375.0535
    },
    "55_2": {
      "nm": "Economy car",
      "vw": 2400.228
    },
    "55_3": {
      "nm": "Economy car",
      "vw": 2500
    },
    "55_4": {
      "nm": "Economy car",
      "vw": 2489.992
    },
    "55_5": {
      "nm": "Economy car",
      "vw": 2490
    },
    "55_6": {
      "nm": "Economy car",
      "vw": 2580
    },
    "55_7": {
      "nm": "Economy car",
      "vw": 2600
    },
    "56_0": {
      "nm": "Luxury car",
      "vw": 4537.8096
    },
    "56_1": {
      "nm": "Luxury car",
      "vw": 4590
    },
    "56_2": {
      "nm": "Luxury car",
      "vw": 4556.892
    },
    "56_3": {
      "nm": "Luxury car",
      "vw": 4579.6875
    },
    "56_4": {
      "nm": "Luxury car",
      "vw": 4637.7705
    },
    "56_5": {
      "nm": "Luxury car",
      "vw": 4710.606
    },
    "56_6": {
      "nm": "Luxury car",
      "vw": 4870
    },
    "56_7": {
      "nm": "Luxury car",
      "vw": 4950.4653
    },
    "56_8": {
      "nm": "Luxury car",
      "vw": 5000
    },
    "57_0": {
      "nm": "Truck",
      "vw": 6117.3613
    },
    "57_1": {
      "nm": "Truck",
      "vw": 6095.777
    },
    "57_2": {
      "nm": "Truck",
      "vw": 6101.368
    },
    "57_3": {
      "nm": "Truck",
      "vw": 6143.353
    },
    "57_4": {
      "nm": "Truck",
      "vw": 6274.035
    },
    "57_5": {
      "nm": "Truck",
      "vw": 6322.222
    },
    "57_6": {
      "nm": "Truck",
      "vw": 6375
    },
    "58_0": {
      "nm": "Automotive research",
      "vw": 153.7264
    },
    "59_0": {
      "nm": "Fashion research",
      "vw": 68.043
    },
    "5_0": {
      "nm": "Grapes",
      "vw": 3.9858
    },
    "5_1": {
      "nm": "Grapes",
      "vw": 3.8377
    },
    "5_10": {
      "nm": "Grapes",
      "vw": 7
    },
    "5_2": {
      "nm": "Grapes",
      "vw": 4.0576
    },
    "5_3": {
      "nm": "Grapes",
      "vw": 4.7501
    },
    "5_4": {
      "nm": "Grapes",
      "vw": 4.0901
    },
    "5_5": {
      "nm": "Grapes",
      "vw": 5.1679
    },
    "5_6": {
      "nm": "Grapes",
      "vw": 6
    },
    "60_0": {
      "nm": "Underwear",
      "vw": 6.7404
    },
    "60_1": {
      "nm": "Underwear",
      "vw": 6.8343
    },
    "60_12": {
      "nm": "Underwear",
      "vw": 12.4276
    },
    "60_2": {
      "nm": "Underwear",
      "vw": 6.8746
    },
    "60_3": {
      "nm": "Underwear",
      "vw": 6.9302
    },
    "60_4": {
      "nm": "Underwear",
      "vw": 6.9625
    },
    "60_5": {
      "nm": "Underwear",
      "vw": 7.2217
    },
    "60_6": {
      "nm": "Underwear",
      "vw": 7.7906
    },
    "60_7": {
      "nm": "Underwear",
      "vw": 7.7
    },
    "60_8": {
      "nm": "Underwear",
      "vw": 7.9664
    },
    "60_9": {
      "nm": "Underwear",
      "vw": 11
    },
    "61_0": {
      "nm": "Gloves",
      "vw": 19.2156
    },
    "61_1": {
      "nm": "Gloves",
      "vw": 19.6072
    },
    "61_2": {
      "nm": "Gloves",
      "vw": 19.562
    },
    "61_3": {
      "nm": "Gloves",
      "vw": 19.7036
    },
    "61_4": {
      "nm": "Gloves",
      "vw": 20.3092
    },
    "61_5": {
      "nm": "Gloves",
      "vw": 20.3583
    },
    "61_6": {
      "nm": "Gloves",
      "vw": 21.7915
    },
    "61_7": {
      "nm": "Gloves",
      "vw": 20.1471
    },
    "62_0": {
      "nm": "Dress",
      "vw": 23.4632
    },
    "62_1": {
      "nm": "Dress",
      "vw": 23.789
    },
    "62_2": {
      "nm": "Dress",
      "vw": 24.0138
    },
    "62_3": {
      "nm": "Dress",
      "vw": 24.307
    },
    "62_4": {
      "nm": "Dress",
      "vw": 24.7048
    },
    "62_5": {
      "nm": "Dress",
      "vw": 25.5
    },
    "62_6": {
      "nm": "Dress",
      "vw": 27.5
    },
    "62_7": {
      "nm": "Dress",
      "vw": 29.5
    },
    "63_0": {
      "nm": "Stiletto Heel",
      "vw": 34.9095
    },
    "63_1": {
      "nm": "Stiletto Heel",
      "vw": 35.3089
    },
    "63_2": {
      "nm": "Stiletto Heel",
      "vw": 35.1415
    },
    "63_3": {
      "nm": "Stiletto Heel",
      "vw": 35.7332
    },
    "63_4": {
      "nm": "Stiletto Heel",
      "vw": 35.9901
    },
    "63_5": {
      "nm": "Stiletto Heel",
      "vw": 36.122
    },
    "63_6": {
      "nm": "Stiletto Heel",
      "vw": 36.5
    },
    "64_0": {
      "nm": "Handbags",
      "vw": 46.1585
    },
    "64_1": {
      "nm": "Handbags",
      "vw": 46.1577
    },
    "64_2": {
      "nm": "Handbags",
      "vw": 47.019
    },
    "64_3": {
      "nm": "Handbags",
      "vw": 48.6751
    },
    "64_4": {
      "nm": "Handbags",
      "vw": 49.25
    },
    "64_5": {
      "nm": "Handbags",
      "vw": 49.6126
    },
    "64_6": {
      "nm": "Handbags",
      "vw": 45.7139
    },
    "64_7": {
      "nm": "Handbags",
      "vw": 50
    },
    "64_9": {
      "nm": "Handbags",
      "vw": 60
    },
    "65_0": {
      "nm": "Sneakers",
      "vw": 15.8195
    },
    "65_1": {
      "nm": "Sneakers",
      "vw": 15.6148
    },
    "65_10": {
      "nm": "Sneakers",
      "vw": 18.5
    },
    "65_11": {
      "nm": "Sneakers",
      "vw": 19.2
    },
    "65_12": {
      "nm": "Sneakers",
      "vw": 20
    },
    "65_2": {
      "nm": "Sneakers",
      "vw": 15.7964
    },
    "65_3": {
      "nm": "Sneakers",
      "vw": 15.863
    },
    "65_4": {
      "nm": "Sneakers",
      "vw": 16.1138
    },
    "65_5": {
      "nm": "Sneakers",
      "vw": 16.1
    },
    "65_6": {
      "nm": "Sneakers",
      "vw": 16.767
    },
    "65_7": {
      "nm": "Sneakers",
      "vw": 16.8545
    },
    "65_8": {
      "nm": "Sneakers",
      "vw": 18.7
    },
    "65_9": {
      "nm": "Sneakers",
      "vw": 18.9
    },
    "66_0": {
      "nm": "Seeds",
      "vw": 0.2695
    },
    "66_1": {
      "nm": "Seeds",
      "vw": 0.273
    },
    "66_10": {
      "nm": "Seeds",
      "vw": 0.6828
    },
    "66_11": {
      "nm": "Seeds",
      "vw": 1.04
    },
    "66_2": {
      "nm": "Seeds",
      "vw": 0.2861
    },
    "66_3": {
      "nm": "Seeds",
      "vw": 0.3584
    },
    "66_4": {
      "nm": "Seeds",
      "vw": 0.3648
    },
    "66_5": {
      "nm": "Seeds",
      "vw": 0.3714
    },
    "66_6": {
      "nm": "Seeds",
      "vw": 0.4163
    },
    "66_7": {
      "nm": "Seeds",
      "vw": 0.4111
    },
    "66_8": {
      "nm": "Seeds",
      "vw": 0.5522
    },
    "66_9": {
      "nm": "Seeds",
      "vw": 0.785
    },
    "67_0": {
      "nm": "Xmas crackers",
      "vw": 12.913
    },
    "67_2": {
      "nm": "Xmas crackers",
      "vw": 16.5
    },
    "67_3": {
      "nm": "Xmas crackers",
      "vw": 13.6
    },
    "67_4": {
      "nm": "Xmas crackers",
      "vw": 22
    },
    "67_6": {
      "nm": "Xmas crackers",
      "vw": 13.7
    },
    "68_0": {
      "nm": "Gold ore",
      "vw": 33.6868
    },
    "68_1": {
      "nm": "Gold ore",
      "vw": 33.8914
    },
    "68_10": {
      "nm": "Gold ore",
      "vw": 38.2483
    },
    "68_2": {
      "nm": "Gold ore",
      "vw": 34.3268
    },
    "68_3": {
      "nm": "Gold ore",
      "vw": 35.3583
    },
    "68_4": {
      "nm": "Gold ore",
      "vw": 35.5344
    },
    "68_5": {
      "nm": "Gold ore",
      "vw": 38.5
    },
    "68_6": {
      "nm": "Gold ore",
      "vw": 38
    },
    "69_0": {
      "nm": "Golden bars",
      "vw": 6666.897
    },
    "69_1": {
      "nm": "Golden bars",
      "vw": 6801.6045
    },
    "69_10": {
      "nm": "Golden bars",
      "vw": 8725
    },
    "69_11": {
      "nm": "Golden bars",
      "vw": 8975
    },
    "69_12": {
      "nm": "Golden bars",
      "vw": 14000
    },
    "69_2": {
      "nm": "Golden bars",
      "vw": 6925.2944
    },
    "69_3": {
      "nm": "Golden bars",
      "vw": 6999.4697
    },
    "69_4": {
      "nm": "Golden bars",
      "vw": 7092.593
    },
    "69_5": {
      "nm": "Golden bars",
      "vw": 7276.6055
    },
    "69_6": {
      "nm": "Golden bars",
      "vw": 7743.2383
    },
    "69_7": {
      "nm": "Golden bars",
      "vw": 7781.158
    },
    "69_8": {
      "nm": "Golden bars",
      "vw": 7800
    },
    "69_9": {
      "nm": "Golden bars",
      "vw": 8371.061
    },
    "6_0": {
      "nm": "Grain",
      "vw": 0.6986
    },
    "6_1": {
      "nm": "Grain",
      "vw": 0.7055
    },
    "6_12": {
      "nm": "Grain",
      "vw": 3.4995
    },
    "6_2": {
      "nm": "Grain",
      "vw": 0.7448
    },
    "6_3": {
      "nm": "Grain",
      "vw": 0.7667
    },
    "6_4": {
      "nm": "Grain",
      "vw": 0.8034
    },
    "6_5": {
      "nm": "Grain",
      "vw": 0.7777
    },
    "6_6": {
      "nm": "Grain",
      "vw": 0.925
    },
    "6_7": {
      "nm": "Grain",
      "vw": 1.2496
    },
    "6_8": {
      "nm": "Grain",
      "vw": 1.743
    },
    "6_9": {
      "nm": "Grain",
      "vw": 2
    },
    "70_0": {
      "nm": "Luxury watch",
      "vw": 849.4313
    },
    "70_1": {
      "nm": "Luxury watch",
      "vw": 859.481
    },
    "70_10": {
      "nm": "Luxury watch",
      "vw": 1263
    },
    "70_2": {
      "nm": "Luxury watch",
      "vw": 850.5062
    },
    "70_3": {
      "nm": "Luxury watch",
      "vw": 872.3557
    },
    "70_4": {
      "nm": "Luxury watch",
      "vw": 880
    },
    "70_5": {
      "nm": "Luxury watch",
      "vw": 873.2958
    },
    "70_6": {
      "nm": "Luxury watch",
      "vw": 843.9345
    },
    "70_8": {
      "nm": "Luxury watch",
      "vw": 1100
    },
    "71_0": {
      "nm": "Necklace",
      "vw": 1697.4506
    },
    "71_1": {
      "nm": "Necklace",
      "vw": 1705.737
    },
    "71_11": {
      "nm": "Necklace",
      "vw": 2750
    },
    "71_2": {
      "nm": "Necklace",
      "vw": 1715.4697
    },
    "71_3": {
      "nm": "Necklace",
      "vw": 1742.3015
    },
    "71_4": {
      "nm": "Necklace",
      "vw": 1759.3905
    },
    "71_5": {
      "nm": "Necklace",
      "vw": 1860
    },
    "71_6": {
      "nm": "Necklace",
      "vw": 1860
    },
    "72_0": {
      "nm": "Sugarcane",
      "vw": 1.7248
    },
    "72_1": {
      "nm": "Sugarcane",
      "vw": 1.7637
    },
    "72_10": {
      "nm": "Sugarcane",
      "vw": 6
    },
    "72_2": {
      "nm": "Sugarcane",
      "vw": 1.7782
    },
    "72_3": {
      "nm": "Sugarcane",
      "vw": 1.7905
    },
    "72_4": {
      "nm": "Sugarcane",
      "vw": 1.9148
    },
    "72_5": {
      "nm": "Sugarcane",
      "vw": 1.9741
    },
    "72_6": {
      "nm": "Sugarcane",
      "vw": 2.5566
    },
    "72_7": {
      "nm": "Sugarcane",
      "vw": 2.65
    },
    "72_8": {
      "nm": "Sugarcane",
      "vw": 4
    },
    "72_9": {
      "nm": "Sugarcane",
      "vw": 3.5
    },
    "73_0": {
      "nm": "Ethanol",
      "vw": 26.5164
    },
    "73_1": {
      "nm": "Ethanol",
      "vw": 27.9143
    },
    "73_10": {
      "nm": "Ethanol",
      "vw": 33.75
    },
    "73_2": {
      "nm": "Ethanol",
      "vw": 28.6238
    },
    "73_3": {
      "nm": "Ethanol",
      "vw": 30.1487
    },
    "73_4": {
      "nm": "Ethanol",
      "vw": 30.864
    },
    "73_5": {
      "nm": "Ethanol",
      "vw": 32.2256
    },
    "73_6": {
      "nm": "Ethanol",
      "vw": 32.75
    },
    "73_8": {
      "nm": "Ethanol",
      "vw": 33.75
    },
    "74_0": {
      "nm": "Methane",
      "vw": 19.8931
    },
    "74_1": {
      "nm": "Methane",
      "vw": 21.3392
    },
    "74_12": {
      "nm": "Methane",
      "vw": 30
    },
    "74_2": {
      "nm": "Methane",
      "vw": 21.8212
    },
    "74_3": {
      "nm": "Methane",
      "vw": 21.9152
    },
    "74_4": {
      "nm": "Methane",
      "vw": 22.032
    },
    "74_5": {
      "nm": "Methane",
      "vw": 22.5
    },
    "74_6": {
      "nm": "Methane",
      "vw": 22
    },
    "74_7": {
      "nm": "Methane",
      "vw": 22
    },
    "74_8": {
      "nm": "Methane",
      "vw": 30
    },
    "75_0": {
      "nm": "Carbon fibers",
      "vw": 6.8494
    },
    "75_1": {
      "nm": "Carbon fibers",
      "vw": 7.1488
    },
    "75_10": {
      "nm": "Carbon fibers",
      "vw": 7.7
    },
    "75_11": {
      "nm": "Carbon fibers",
      "vw": 7.3
    },
    "75_2": {
      "nm": "Carbon fibers",
      "vw": 7.1688
    },
    "75_3": {
      "nm": "Carbon fibers",
      "vw": 7.4306
    },
    "75_4": {
      "nm": "Carbon fibers",
      "vw": 7.5216
    },
    "75_5": {
      "nm": "Carbon fibers",
      "vw": 7.5678
    },
    "75_6": {
      "nm": "Carbon fibers",
      "vw": 7.5851
    },
    "75_7": {
      "nm": "Carbon fibers",
      "vw": 7.6237
    },
    "75_8": {
      "nm": "Carbon fibers",
      "vw": 7.7495
    },
    "75_9": {
      "nm": "Carbon fibers",
      "vw": 7.7
    },
    "76_0": {
      "nm": "Carbon composite",
      "vw": 66.3696
    },
    "76_1": {
      "nm": "Carbon composite",
      "vw": 68.2664
    },
    "76_10": {
      "nm": "Carbon composite",
      "vw": 84.1676
    },
    "76_11": {
      "nm": "Carbon composite",
      "vw": 84
    },
    "76_12": {
      "nm": "Carbon composite",
      "vw": 100
    },
    "76_2": {
      "nm": "Carbon composite",
      "vw": 69.0459
    },
    "76_3": {
      "nm": "Carbon composite",
      "vw": 69.6274
    },
    "76_4": {
      "nm": "Carbon composite",
      "vw": 71.0778
    },
    "76_5": {
      "nm": "Carbon composite",
      "vw": 74.994
    },
    "76_6": {
      "nm": "Carbon composite",
      "vw": 78.4564
    },
    "76_7": {
      "nm": "Carbon composite",
      "vw": 75.1662
    },
    "76_8": {
      "nm": "Carbon composite",
      "vw": 76.0072
    },
    "76_9": {
      "nm": "Carbon composite",
      "vw": 80.6046
    },
    "77_0": {
      "nm": "Fuselage",
      "vw": 2943.136
    },
    "77_1": {
      "nm": "Fuselage",
      "vw": 3023.4438
    },
    "77_10": {
      "nm": "Fuselage",
      "vw": 3430
    },
    "77_2": {
      "nm": "Fuselage",
      "vw": 3038.6665
    },
    "77_3": {
      "nm": "Fuselage",
      "vw": 3056.1846
    },
    "77_4": {
      "nm": "Fuselage",
      "vw": 3065.0227
    },
    "77_5": {
      "nm": "Fuselage",
      "vw": 3104.6567
    },
    "77_6": {
      "nm": "Fuselage",
      "vw": 3300
    },
    "77_7": {
      "nm": "Fuselage",
      "vw": 3133.2322
    },
    "77_8": {
      "nm": "Fuselage",
      "vw": 3367.9375
    },
    "78_0": {
      "nm": "Wing",
      "vw": 2139.1929
    },
    "78_1": {
      "nm": "Wing",
      "vw": 2338.4805
    },
    "78_10": {
      "nm": "Wing",
      "vw": 2685
    },
    "78_2": {
      "nm": "Wing",
      "vw": 2363.403
    },
    "78_3": {
      "nm": "Wing",
      "vw": 2377.0862
    },
    "78_4": {
      "nm": "Wing",
      "vw": 2383.8447
    },
    "78_5": {
      "nm": "Wing",
      "vw": 2421.7583
    },
    "78_6": {
      "nm": "Wing",
      "vw": 2540.5957
    },
    "78_7": {
      "nm": "Wing",
      "vw": 2576.044
    },
    "78_8": {
      "nm": "Wing",
      "vw": 2590
    },
    "78_9": {
      "nm": "Wing",
      "vw": 2597.5
    },
    "79_0": {
      "nm": "High grade e-comps",
      "vw": 894.6077
    },
    "79_1": {
      "nm": "High grade e-comps",
      "vw": 902.0295
    },
    "79_10": {
      "nm": "High grade e-comps",
      "vw": 1044.9238
    },
    "79_11": {
      "nm": "High grade e-comps",
      "vw": 1010
    },
    "79_12": {
      "nm": "High grade e-comps",
      "vw": 1560
    },
    "79_2": {
      "nm": "High grade e-comps",
      "vw": 911.4797
    },
    "79_3": {
      "nm": "High grade e-comps",
      "vw": 913.8619
    },
    "79_4": {
      "nm": "High grade e-comps",
      "vw": 923.7532
    },
    "79_5": {
      "nm": "High grade e-comps",
      "vw": 938.4308
    },
    "79_6": {
      "nm": "High grade e-comps",
      "vw": 958.8165
    },
    "79_7": {
      "nm": "High grade e-comps",
      "vw": 979.1328
    },
    "79_8": {
      "nm": "High grade e-comps",
      "vw": 998.6957
    },
    "79_9": {
      "nm": "High grade e-comps",
      "vw": 1020
    },
    "7_0": {
      "nm": "Steak",
      "vw": 43.316
    },
    "7_1": {
      "nm": "Steak",
      "vw": 43.8592
    },
    "7_2": {
      "nm": "Steak",
      "vw": 44.1249
    },
    "7_3": {
      "nm": "Steak",
      "vw": 44.5764
    },
    "7_4": {
      "nm": "Steak",
      "vw": 44.0161
    },
    "7_5": {
      "nm": "Steak",
      "vw": 49
    },
    "7_6": {
      "nm": "Steak",
      "vw": 49.2359
    },
    "7_7": {
      "nm": "Steak",
      "vw": 49.5
    },
    "7_8": {
      "nm": "Steak",
      "vw": 55
    },
    "80_0": {
      "nm": "Flight computer",
      "vw": 5229.4116
    },
    "80_1": {
      "nm": "Flight computer",
      "vw": 5416.6665
    },
    "80_2": {
      "nm": "Flight computer",
      "vw": 5320.78
    },
    "80_3": {
      "nm": "Flight computer",
      "vw": 5387.4873
    },
    "80_4": {
      "nm": "Flight computer",
      "vw": 5367.9526
    },
    "80_5": {
      "nm": "Flight computer",
      "vw": 5568.052
    },
    "80_6": {
      "nm": "Flight computer",
      "vw": 5654.338
    },
    "80_7": {
      "nm": "Flight computer",
      "vw": 5631.8384
    },
    "80_9": {
      "nm": "Flight computer",
      "vw": 5532.9546
    },
    "81_0": {
      "nm": "Cockpit",
      "vw": 5588.614
    },
    "81_1": {
      "nm": "Cockpit",
      "vw": 5637.9746
    },
    "81_10": {
      "nm": "Cockpit",
      "vw": 6750
    },
    "81_11": {
      "nm": "Cockpit",
      "vw": 7010
    },
    "81_2": {
      "nm": "Cockpit",
      "vw": 5626.151
    },
    "81_3": {
      "nm": "Cockpit",
      "vw": 5619.4473
    },
    "81_4": {
      "nm": "Cockpit",
      "vw": 5638.656
    },
    "81_5": {
      "nm": "Cockpit",
      "vw": 5764.8975
    },
    "81_6": {
      "nm": "Cockpit",
      "vw": 5820.2754
    },
    "81_7": {
      "nm": "Cockpit",
      "vw": 6325
    },
    "81_8": {
      "nm": "Cockpit",
      "vw": 6400
    },
    "81_9": {
      "nm": "Cockpit",
      "vw": 6500
    },
    "82_0": {
      "nm": "Attitude control",
      "vw": 1641.1428
    },
    "82_1": {
      "nm": "Attitude control",
      "vw": 1642.7098
    },
    "82_10": {
      "nm": "Attitude control",
      "vw": 2200
    },
    "82_2": {
      "nm": "Attitude control",
      "vw": 1656.3894
    },
    "82_3": {
      "nm": "Attitude control",
      "vw": 1686.2345
    },
    "82_4": {
      "nm": "Attitude control",
      "vw": 1687.9883
    },
    "82_5": {
      "nm": "Attitude control",
      "vw": 1718.2428
    },
    "82_6": {
      "nm": "Attitude control",
      "vw": 1690
    },
    "82_7": {
      "nm": "Attitude control",
      "vw": 1796.2052
    },
    "82_9": {
      "nm": "Attitude control",
      "vw": 1945.3866
    },
    "83_0": {
      "nm": "Rocket fuel",
      "vw": 31.2696
    },
    "83_1": {
      "nm": "Rocket fuel",
      "vw": 33.1658
    },
    "83_2": {
      "nm": "Rocket fuel",
      "vw": 33.2497
    },
    "83_3": {
      "nm": "Rocket fuel",
      "vw": 33.6147
    },
    "83_4": {
      "nm": "Rocket fuel",
      "vw": 34.4076
    },
    "83_5": {
      "nm": "Rocket fuel",
      "vw": 35.7273
    },
    "83_6": {
      "nm": "Rocket fuel",
      "vw": 36.9915
    },
    "83_7": {
      "nm": "Rocket fuel",
      "vw": 37.5
    },
    "83_8": {
      "nm": "Rocket fuel",
      "vw": 47
    },
    "84_0": {
      "nm": "Propellant tank",
      "vw": 8837.461
    },
    "84_1": {
      "nm": "Propellant tank",
      "vw": 9480.33
    },
    "84_2": {
      "nm": "Propellant tank",
      "vw": 9705.332
    },
    "84_3": {
      "nm": "Propellant tank",
      "vw": 10037.713
    },
    "84_4": {
      "nm": "Propellant tank",
      "vw": 10070.37
    },
    "84_5": {
      "nm": "Propellant tank",
      "vw": 10193.579
    },
    "84_6": {
      "nm": "Propellant tank",
      "vw": 10938.607
    },
    "84_7": {
      "nm": "Propellant tank",
      "vw": 11600
    },
    "84_8": {
      "nm": "Propellant tank",
      "vw": 12000
    },
    "85_0": {
      "nm": "Solid fuel booster",
      "vw": 7849.1377
    },
    "85_1": {
      "nm": "Solid fuel booster",
      "vw": 8350
    },
    "85_2": {
      "nm": "Solid fuel booster",
      "vw": 8417.593
    },
    "85_3": {
      "nm": "Solid fuel booster",
      "vw": 8963.365
    },
    "85_4": {
      "nm": "Solid fuel booster",
      "vw": 8999.339
    },
    "85_5": {
      "nm": "Solid fuel booster",
      "vw": 10011.429
    },
    "85_6": {
      "nm": "Solid fuel booster",
      "vw": 10900
    },
    "85_7": {
      "nm": "Solid fuel booster",
      "vw": 11000
    },
    "85_8": {
      "nm": "Solid fuel booster",
      "vw": 11600
    },
    "86_0": {
      "nm": "Rocket engine",
      "vw": 11713.924
    },
    "86_1": {
      "nm": "Rocket engine",
      "vw": 11732.5
    },
    "86_2": {
      "nm": "Rocket engine",
      "vw": 11943.934
    },
    "86_3": {
      "nm": "Rocket engine",
      "vw": 12039.474
    },
    "86_4": {
      "nm": "Rocket engine",
      "vw": 12001.64
    },
    "86_5": {
      "nm": "Rocket engine",
      "vw": 12102.408
    },
    "86_6": {
      "nm": "Rocket engine",
      "vw": 12200
    },
    "86_7": {
      "nm": "Rocket engine",
      "vw": 13460.475
    },
    "86_8": {
      "nm": "Rocket engine",
      "vw": 12502.516
    },
    "86_9": {
      "nm": "Rocket engine",
      "vw": 13650.505
    },
    "87_0": {
      "nm": "Heat shield",
      "vw": 457.4167
    },
    "87_1": {
      "nm": "Heat shield",
      "vw": 472.8
    },
    "87_2": {
      "nm": "Heat shield",
      "vw": 514.7683
    },
    "87_3": {
      "nm": "Heat shield",
      "vw": 539.247
    },
    "87_4": {
      "nm": "Heat shield",
      "vw": 548.3408
    },
    "87_5": {
      "nm": "Heat shield",
      "vw": 546.5952
    },
    "87_6": {
      "nm": "Heat shield",
      "vw": 692
    },
    "87_8": {
      "nm": "Heat shield",
      "vw": 850
    },
    "88_0": {
      "nm": "Ion drive",
      "vw": 11678.922
    },
    "88_1": {
      "nm": "Ion drive",
      "vw": 12117.561
    },
    "88_10": {
      "nm": "Ion drive",
      "vw": 12800
    },
    "88_2": {
      "nm": "Ion drive",
      "vw": 12246.809
    },
    "88_3": {
      "nm": "Ion drive",
      "vw": 12396.907
    },
    "88_4": {
      "nm": "Ion drive",
      "vw": 12544.878
    },
    "88_5": {
      "nm": "Ion drive",
      "vw": 12342.857
    },
    "88_6": {
      "nm": "Ion drive",
      "vw": 12808.814
    },
    "88_7": {
      "nm": "Ion drive",
      "vw": 13300
    },
    "88_8": {
      "nm": "Ion drive",
      "vw": 13585.714
    },
    "88_9": {
      "nm": "Ion drive",
      "vw": 12800
    },
    "89_0": {
      "nm": "Jet engine",
      "vw": 5377.778
    },
    "89_1": {
      "nm": "Jet engine",
      "vw": 5383.5337
    },
    "89_10": {
      "nm": "Jet engine",
      "vw": 5925
    },
    "89_2": {
      "nm": "Jet engine",
      "vw": 5451.688
    },
    "89_3": {
      "nm": "Jet engine",
      "vw": 5502.8413
    },
    "89_4": {
      "nm": "Jet engine",
      "vw": 5625.308
    },
    "89_5": {
      "nm": "Jet engine",
      "vw": 5644.3438
    },
    "89_6": {
      "nm": "Jet engine",
      "vw": 5875
    },
    "89_7": {
      "nm": "Jet engine",
      "vw": 5900
    },
    "89_8": {
      "nm": "Jet engine",
      "vw": 5875
    },
    "8_0": {
      "nm": "Sausages",
      "vw": 12.5909
    },
    "8_1": {
      "nm": "Sausages",
      "vw": 12.7016
    },
    "8_2": {
      "nm": "Sausages",
      "vw": 12.8845
    },
    "8_3": {
      "nm": "Sausages",
      "vw": 12.9711
    },
    "8_4": {
      "nm": "Sausages",
      "vw": 13.4
    },
    "8_5": {
      "nm": "Sausages",
      "vw": 13.0099
    },
    "8_6": {
      "nm": "Sausages",
      "vw": 14.5
    },
    "8_7": {
      "nm": "Sausages",
      "vw": 14.1
    },
    "98_0": {
      "nm": "Quadcopter",
      "vw": 913.9764
    },
    "98_1": {
      "nm": "Quadcopter",
      "vw": 916.0101
    },
    "98_2": {
      "nm": "Quadcopter",
      "vw": 917.7938
    },
    "98_3": {
      "nm": "Quadcopter",
      "vw": 928.1348
    },
    "98_4": {
      "nm": "Quadcopter",
      "vw": 941.029
    },
    "98_5": {
      "nm": "Quadcopter",
      "vw": 955.227
    },
    "98_6": {
      "nm": "Quadcopter",
      "vw": 1027.2727
    },
    "98_7": {
      "nm": "Quadcopter",
      "vw": 1020
    },
    "9_0": {
      "nm": "Eggs",
      "vw": 1.2616
    },
    "9_1": {
      "nm": "Eggs",
      "vw": 1.2976
    },
    "9_10": {
      "nm": "Eggs",
      "vw": 3
    },
    "9_12": {
      "nm": "Eggs",
      "vw": 3
    },
    "9_2": {
      "nm": "Eggs",
      "vw": 1.3318
    },
    "9_3": {
      "nm": "Eggs",
      "vw": 1.3478
    },
    "9_4": {
      "nm": "Eggs",
      "vw": 1.422
    },
    "9_5": {
      "nm": "Eggs",
      "vw": 1.5886
    },
    "9_7": {
      "nm": "Eggs",
      "vw": 1.8613
    },
    "9_9": {
      "nm": "Eggs",
      "vw": 2.4384
    }
  },
  "overall": {
    "n": 142,
    "vw": 924.2138
  },
  "product": {
    "1": {
      "nm": "Power",
      "vw": 0.2719
    },
    "10": {
      "nm": "Crude oil",
      "vw": 30.7267
    },
    "100": {
      "nm": "Aerospace research",
      "vw": 126.8875
    },
    "101": {
      "nm": "Reinforced concrete",
      "vw": 198.1025
    },
    "102": {
      "nm": "Bricks",
      "vw": 2.751
    },
    "103": {
      "nm": "Cement",
      "vw": 6.8792
    },
    "104": {
      "nm": "Clay",
      "vw": 1.0562
    },
    "105": {
      "nm": "Limestone",
      "vw": 1.6392
    },
    "106": {
      "nm": "Wood",
      "vw": 3.8901
    },
    "107": {
      "nm": "Beams",
      "vw": 21.406
    },
    "108": {
      "nm": "Planks",
      "vw": 9.9666
    },
    "109": {
      "nm": "Windows",
      "vw": 113.4606
    },
    "11": {
      "nm": "Petrol",
      "vw": 42.7692
    },
    "110": {
      "nm": "Tools",
      "vw": 205.5737
    },
    "111": {
      "nm": "Construction units",
      "vw": 2674.2778
    },
    "112": {
      "nm": "Bulldozer",
      "vw": 2354.9133
    },
    "113": {
      "nm": "Materials research",
      "vw": 148.801
    },
    "114": {
      "nm": "Robots",
      "vw": 647.0446
    },
    "115": {
      "nm": "Cows",
      "vw": 129.8444
    },
    "116": {
      "nm": "Pigs",
      "vw": 41.9601
    },
    "117": {
      "nm": "Milk",
      "vw": 8.0181
    },
    "118": {
      "nm": "Coffee beans",
      "vw": 0.8378
    },
    "119": {
      "nm": "Coffee powder",
      "vw": 34.5965
    },
    "12": {
      "nm": "Diesel",
      "vw": 43.4511
    },
    "120": {
      "nm": "Vegetables",
      "vw": 2.7038
    },
    "121": {
      "nm": "Bread",
      "vw": 152.6942
    },
    "122": {
      "nm": "Cheese",
      "vw": 132.956
    },
    "123": {
      "nm": "Apple pie",
      "vw": 319.874
    },
    "124": {
      "nm": "Orange juice",
      "vw": 38.066
    },
    "125": {
      "nm": "Apple cider",
      "vw": 26.9784
    },
    "126": {
      "nm": "Ginger beer",
      "vw": 53.9331
    },
    "127": {
      "nm": "Frozen pizza",
      "vw": 497.131
    },
    "128": {
      "nm": "Pasta",
      "vw": 58.5282
    },
    "129": {
      "nm": "Hamburger",
      "vw": 2368.362
    },
    "13": {
      "nm": "Transport",
      "vw": 0.3937
    },
    "130": {
      "nm": "Lasagna",
      "vw": 2335.5657
    },
    "131": {
      "nm": "Meat balls",
      "vw": 2376.1982
    },
    "132": {
      "nm": "Cocktails",
      "vw": 2388.5547
    },
    "133": {
      "nm": "Flour",
      "vw": 17.7302
    },
    "134": {
      "nm": "Butter",
      "vw": 56.8536
    },
    "135": {
      "nm": "Sugar",
      "vw": 19.3872
    },
    "136": {
      "nm": "Cocoa",
      "vw": 1.6286
    },
    "137": {
      "nm": "Dough",
      "vw": 133.3443
    },
    "138": {
      "nm": "Sauce",
      "vw": 1341.16
    },
    "139": {
      "nm": "Fodder",
      "vw": 11.633
    },
    "14": {
      "nm": "Minerals",
      "vw": 11.9988
    },
    "140": {
      "nm": "Chocolate",
      "vw": 258.0811
    },
    "141": {
      "nm": "Vegetable oil",
      "vw": 37.354
    },
    "142": {
      "nm": "Salad",
      "vw": 829.8611
    },
    "143": {
      "nm": "Samosa",
      "vw": 734.6744
    },
    "144": {
      "nm": "Xmas ornament",
      "vw": 18.1706
    },
    "145": {
      "nm": "Recipes",
      "vw": 141.2504
    },
    "146": {
      "nm": "Pumpkin",
      "vw": 12.2849
    },
    "147": {
      "nm": "Jack o'lantern",
      "vw": 46.4999
    },
    "148": {
      "nm": "Witch costume",
      "vw": 35.1916
    },
    "149": {
      "nm": "Pumpkin soup",
      "vw": 900.9722
    },
    "15": {
      "nm": "Bauxite",
      "vw": 10.93
    },
    "150": {
      "nm": "Tree",
      "vw": 331.0367
    },
    "151": {
      "nm": "Easter Bunny",
      "vw": 242.6533
    },
    "152": {
      "nm": "Ramadan sweets",
      "vw": 226
    },
    "153": {
      "nm": "Chocolate icecream",
      "vw": 75.8946
    },
    "154": {
      "nm": "Apple icecream",
      "vw": 86.0581
    },
    "155": {
      "nm": "Cream egg",
      "vw": 134.8613
    },
    "16": {
      "nm": "Silicon",
      "vw": 8.4886
    },
    "17": {
      "nm": "Chemicals",
      "vw": 15.7649
    },
    "18": {
      "nm": "Aluminium",
      "vw": 21.0536
    },
    "19": {
      "nm": "Plastic",
      "vw": 12.6631
    },
    "2": {
      "nm": "Water",
      "vw": 0.3873
    },
    "20": {
      "nm": "Processors",
      "vw": 118.8226
    },
    "21": {
      "nm": "Electronic components",
      "vw": 58.6553
    },
    "22": {
      "nm": "Batteries",
      "vw": 91.3419
    },
    "23": {
      "nm": "Displays",
      "vw": 129.6532
    },
    "24": {
      "nm": "Smart phones",
      "vw": 642.904
    },
    "25": {
      "nm": "Tablets",
      "vw": 805.5586
    },
    "26": {
      "nm": "Laptops",
      "vw": 1277.4202
    },
    "27": {
      "nm": "Monitors",
      "vw": 591.7982
    },
    "28": {
      "nm": "Televisions",
      "vw": 992.6899
    },
    "29": {
      "nm": "Plant research",
      "vw": 116.3896
    },
    "3": {
      "nm": "Apples",
      "vw": 2.6455
    },
    "30": {
      "nm": "Energy research",
      "vw": 173.6172
    },
    "31": {
      "nm": "Mining research",
      "vw": 194.9817
    },
    "32": {
      "nm": "Electronics research",
      "vw": 238.3211
    },
    "33": {
      "nm": "Breeding research",
      "vw": 126.2903
    },
    "34": {
      "nm": "Chemistry research",
      "vw": 100.0163
    },
    "35": {
      "nm": "Software",
      "vw": 99.8216
    },
    "4": {
      "nm": "Oranges",
      "vw": 2.8137
    },
    "40": {
      "nm": "Cotton",
      "vw": 1.5192
    },
    "41": {
      "nm": "Fabric",
      "vw": 4.5291
    },
    "42": {
      "nm": "Iron ore",
      "vw": 5.1139
    },
    "43": {
      "nm": "Steel",
      "vw": 12.044
    },
    "44": {
      "nm": "Sand",
      "vw": 1.366
    },
    "45": {
      "nm": "Glass",
      "vw": 14.603
    },
    "46": {
      "nm": "Leather",
      "vw": 27.7724
    },
    "47": {
      "nm": "On-board computer",
      "vw": 489.0641
    },
    "48": {
      "nm": "Electric motor",
      "vw": 236.7051
    },
    "49": {
      "nm": "Luxury car interior",
      "vw": 990.5818
    },
    "5": {
      "nm": "Grapes",
      "vw": 3.9858
    },
    "50": {
      "nm": "Basic interior",
      "vw": 350.2583
    },
    "51": {
      "nm": "Car body",
      "vw": 819.0175
    },
    "52": {
      "nm": "Combustion engine",
      "vw": 660.0079
    },
    "53": {
      "nm": "Economy e-car",
      "vw": 3554.9297
    },
    "54": {
      "nm": "Luxury e-car",
      "vw": 6770.421
    },
    "55": {
      "nm": "Economy car",
      "vw": 2398.6633
    },
    "56": {
      "nm": "Luxury car",
      "vw": 4537.8096
    },
    "57": {
      "nm": "Truck",
      "vw": 6117.3613
    },
    "58": {
      "nm": "Automotive research",
      "vw": 153.7264
    },
    "59": {
      "nm": "Fashion research",
      "vw": 68.043
    },
    "6": {
      "nm": "Grain",
      "vw": 0.6986
    },
    "60": {
      "nm": "Underwear",
      "vw": 6.7404
    },
    "61": {
      "nm": "Gloves",
      "vw": 19.2156
    },
    "62": {
      "nm": "Dress",
      "vw": 23.4632
    },
    "63": {
      "nm": "Stiletto Heel",
      "vw": 34.9095
    },
    "64": {
      "nm": "Handbags",
      "vw": 46.1585
    },
    "65": {
      "nm": "Sneakers",
      "vw": 15.8195
    },
    "66": {
      "nm": "Seeds",
      "vw": 0.2695
    },
    "67": {
      "nm": "Xmas crackers",
      "vw": 12.913
    },
    "68": {
      "nm": "Gold ore",
      "vw": 33.6868
    },
    "69": {
      "nm": "Golden bars",
      "vw": 6666.897
    },
    "7": {
      "nm": "Steak",
      "vw": 43.316
    },
    "70": {
      "nm": "Luxury watch",
      "vw": 849.4313
    },
    "71": {
      "nm": "Necklace",
      "vw": 1697.4506
    },
    "72": {
      "nm": "Sugarcane",
      "vw": 1.7248
    },
    "73": {
      "nm": "Ethanol",
      "vw": 26.5164
    },
    "74": {
      "nm": "Methane",
      "vw": 19.8931
    },
    "75": {
      "nm": "Carbon fibers",
      "vw": 6.8494
    },
    "76": {
      "nm": "Carbon composite",
      "vw": 66.3696
    },
    "77": {
      "nm": "Fuselage",
      "vw": 2943.136
    },
    "78": {
      "nm": "Wing",
      "vw": 2139.1929
    },
    "79": {
      "nm": "High grade e-comps",
      "vw": 894.6077
    },
    "8": {
      "nm": "Sausages",
      "vw": 12.5909
    },
    "80": {
      "nm": "Flight computer",
      "vw": 5229.4116
    },
    "81": {
      "nm": "Cockpit",
      "vw": 5588.614
    },
    "82": {
      "nm": "Attitude control",
      "vw": 1641.1428
    },
    "83": {
      "nm": "Rocket fuel",
      "vw": 31.2696
    },
    "84": {
      "nm": "Propellant tank",
      "vw": 8837.461
    },
    "85": {
      "nm": "Solid fuel booster",
      "vw": 7849.1377
    },
    "86": {
      "nm": "Rocket engine",
      "vw": 11713.924
    },
    "87": {
      "nm": "Heat shield",
      "vw": 457.4167
    },
    "88": {
      "nm": "Ion drive",
      "vw": 11678.922
    },
    "89": {
      "nm": "Jet engine",
      "vw": 5377.778
    },
    "9": {
      "nm": "Eggs",
      "vw": 1.2616
    },
    "98": {
      "nm": "Quadcopter",
      "vw": 913.9764
    }
  },
  "quality": {
    "0": {
      "n": 142,
      "vw": 924.2138
    },
    "1": {
      "n": 125,
      "vw": 1038.4739
    },
    "10": {
      "n": 62,
      "vw": 6360.8468
    },
    "11": {
      "n": 37,
      "vw": 18067.0766
    },
    "12": {
      "n": 32,
      "vw": 43491.5527
    },
    "2": {
      "n": 128,
      "vw": 1036.9175
    },
    "3": {
      "n": 125,
      "vw": 1096.1283
    },
    "4": {
      "n": 125,
      "vw": 1124.1233
    },
    "5": {
      "n": 117,
      "vw": 1228.2735
    },
    "6": {
      "n": 111,
      "vw": 1429.3699
    },
    "7": {
      "n": 93,
      "vw": 1816.3943
    },
    "8": {
      "n": 76,
      "vw": 2442.24
    },
    "9": {
      "n": 51,
      "vw": 4543.5421
    }
  },
  "r": 0,
  "t": "2026-07-03"
}
