{
  "fetch": {
    "consecutiveFailures": 0,
    "lastFailure": "2026-07-07T04:25:10.748Z"
  },
  "pipelines": [
    {
      "avgDurationMs": 3,
      "failedRuns": 0,
      "lastOk": true,
      "lastRun": "2026-07-07T04:30:38.967Z",
      "name": "dashboard",
      "totalRuns": 2
    },
    {
      "avgDurationMs": 328069,
      "failedRuns": 1,
      "lastOk": false,
      "lastRun": "2026-07-07T04:30:38.966Z",
      "name": "macro",
      "totalRuns": 1
    },
    {
      "avgDurationMs": 4,
      "failedRuns": 1,
      "lastOk": false,
      "lastRun": "2026-07-07T04:30:38.967Z",
      "name": "intelligence",
      "totalRuns": 1
    },
    {
      "avgDurationMs": 12,
      "failedRuns": 0,
      "lastOk": true,
      "lastRun": "2026-07-07T04:30:38.967Z",
      "name": "relational",
      "totalRuns": 1
    }
  ],
  "scheduler": {
    "running": true,
    "uptimeFormatted": "0h 40m 18s",
    "uptimeMs": 2418795
  },
  "t": "2026-07-07T04:50:33.447Z"
}
