{"t":"2026-06-23T16:55:13.735Z","scheduler":{"running":true,"uptimeMs":6171093,"uptimeFormatted":"1h 42m 51s"},"pipelines":[{"name":"dashboard","lastRun":"2026-06-23T16:35:17.257Z","lastOk":true,"totalRuns":6,"failedRuns":0,"avgDurationMs":2},{"name":"macro","lastRun":"2026-06-23T16:35:17.257Z","lastOk":false,"totalRuns":3,"failedRuns":3,"avgDurationMs":478004},{"name":"intelligence","lastRun":"2026-06-23T16:35:17.257Z","lastOk":true,"totalRuns":3,"failedRuns":2,"avgDurationMs":4},{"name":"relational","lastRun":"2026-06-23T16:35:17.257Z","lastOk":true,"totalRuns":3,"failedRuns":0,"avgDurationMs":8}],"fetch":{"consecutiveFailures":0,"lastFailure":"2026-06-23T16:25:17.005Z"}}

