{"t":"2026-06-24T07:30:28.326Z","scheduler":{"running":true,"uptimeMs":3312456,"uptimeFormatted":"0h 55m 12s"},"pipelines":[{"name":"dashboard","lastRun":"2026-06-24T07:05:14.833Z","lastOk":true,"totalRuns":2,"failedRuns":0,"avgDurationMs":3},{"name":"macro","lastRun":"2026-06-24T07:05:14.833Z","lastOk":false,"totalRuns":1,"failedRuns":1,"avgDurationMs":946945},{"name":"intelligence","lastRun":"2026-06-24T07:05:14.833Z","lastOk":false,"totalRuns":1,"failedRuns":1,"avgDurationMs":7},{"name":"relational","lastRun":"2026-06-24T07:05:14.833Z","lastOk":true,"totalRuns":1,"failedRuns":0,"avgDurationMs":12}],"fetch":{"consecutiveFailures":0,"lastFailure":null}}

