{"t":"2026-06-19T11:35:13.978Z","scheduler":{"running":true,"uptimeMs":5893877,"uptimeFormatted":"1h 38m 13s"},"pipelines":[{"name":"dashboard","lastRun":"2026-06-19T11:10:17.783Z","lastOk":true,"totalRuns":6,"failedRuns":0,"avgDurationMs":1},{"name":"macro","lastRun":"2026-06-19T11:10:17.782Z","lastOk":false,"totalRuns":3,"failedRuns":3,"avgDurationMs":481387},{"name":"intelligence","lastRun":"2026-06-19T11:10:17.783Z","lastOk":true,"totalRuns":3,"failedRuns":2,"avgDurationMs":6},{"name":"relational","lastRun":"2026-06-19T11:10:17.783Z","lastOk":true,"totalRuns":3,"failedRuns":0,"avgDurationMs":9}],"fetch":{"consecutiveFailures":3,"lastFailure":"2026-06-19T11:30:27.403Z"}}

