{
  "fetch": {
    "consecutiveFailures": 1,
    "lastFailure": "2026-06-15T01:50:15.406Z"
  },
  "pipelines": [
    {
      "avgDurationMs": 2,
      "failedRuns": 0,
      "lastOk": true,
      "lastRun": "2026-06-15T01:30:21.638Z",
      "name": "dashboard",
      "totalRuns": 4
    },
    {
      "avgDurationMs": 306708,
      "failedRuns": 2,
      "lastOk": false,
      "lastRun": "2026-06-15T01:30:21.638Z",
      "name": "macro",
      "totalRuns": 2
    },
    {
      "avgDurationMs": 4,
      "failedRuns": 2,
      "lastOk": false,
      "lastRun": "2026-06-15T01:30:21.638Z",
      "name": "intelligence",
      "totalRuns": 2
    },
    {
      "avgDurationMs": 11,
      "failedRuns": 0,
      "lastOk": true,
      "lastRun": "2026-06-15T01:30:21.638Z",
      "name": "relational",
      "totalRuns": 2
    }
  ],
  "scheduler": {
    "running": true,
    "uptimeFormatted": "1h 0m 59s",
    "uptimeMs": 3659807
  },
  "t": "2026-06-15T01:50:44.754Z"
}
