{
  "fetch": {
    "consecutiveFailures": 0,
    "lastFailure": "2026-06-19T16:50:18.584Z"
  },
  "pipelines": [
    {
      "avgDurationMs": 2,
      "failedRuns": 0,
      "lastOk": true,
      "lastRun": "2026-06-19T16:55:15.327Z",
      "name": "dashboard",
      "totalRuns": 6
    },
    {
      "avgDurationMs": 407530,
      "failedRuns": 3,
      "lastOk": false,
      "lastRun": "2026-06-19T16:55:15.326Z",
      "name": "macro",
      "totalRuns": 3
    },
    {
      "avgDurationMs": 4,
      "failedRuns": 3,
      "lastOk": false,
      "lastRun": "2026-06-19T16:55:15.326Z",
      "name": "intelligence",
      "totalRuns": 3
    },
    {
      "avgDurationMs": 9,
      "failedRuns": 0,
      "lastOk": true,
      "lastRun": "2026-06-19T16:55:15.326Z",
      "name": "relational",
      "totalRuns": 3
    }
  ],
  "scheduler": {
    "running": true,
    "uptimeFormatted": "1h 24m 26s",
    "uptimeMs": 5066597
  },
  "t": "2026-06-19T17:05:17.739Z"
}
